{"0001":{"r":"HZ-AIA","t":"B741","f":"00","desc":""},"0002":{"r":"HZ-AIB","t":"B741","f":"00","desc":""},"0003":{"r":"HZ-AIC","t":"B741","f":"00","desc":""},"0004":{"r":"HZ-AID","t":"B741","f":"00","desc":""},"0005":{"r":"HZ-AIE","t":"B741","f":"00","desc":""},"0006":{"r":"HZ-AIF","t":"B74S","f":"00","desc":"Boeing 747 SP68"},"0007":{"r":"HZ-AIG","t":"B741","f":"00","desc":""},"0009":{"r":"HZ-AII","t":"B741","f":"00","desc":""},"000A":{"r":"HZ-AIK","t":"B743","f":"00","desc":""},"000B":{"r":"HZ-AIL","t":"B743","f":"00","desc":""},"000C":{"r":"HZ-AIM","t":"B743","f":"00","desc":""},"000D":{"r":"HZ-AIN","t":"B743","f":"00","desc":""},"000F":{"r":"HZ-AIP","t":"B743","f":"00","desc":""},"0010":{"r":"HZ-AIQ","t":"B743","f":"00","desc":""},"0011":{"r":"HZ-AIR","t":"B743","f":"00","desc":""},"0013":{"r":"HZ-AIT","t":"B743","f":"00","desc":""},"0014":{"r":"HZ-AIU","t":"B742","f":"00","desc":"Boeing 747 268F"},"0015":{"r":"HZ-AIV","t":"B744","f":"00","desc":"Boeing 747 468"},"0016":{"r":"HZ-AIW","t":"B744","f":"00","desc":"Boeing 747 468"},"0017":{"r":"HZ-AIX","t":"B744","f":"00","desc":"Boeing 747 468"},"0018":{"r":"HZ-AIY","t":"B744","f":"00","desc":"Boeing 747 468"},"001A":{"r":"HZ-AI3","t":"B748","f":"00","desc":"Boeing 747 87UF"},"001B":{"r":"HZ-AI4","t":"B748","f":"00","desc":"Boeing 747 87UF"},"001C":{"r":"HMH-1","t":"EH10","f":"00","desc":"EH Industries EH.101 Merlin Mk.640"},"001F":{"r":"HZ-SAAD","t":"C56X","f":"00","desc":"Cessna Citation XLS"},"0020":{"r":"HZ-FJM","t":"CL60","f":"00","desc":"Bombardier Challenger 601 3A"},"0021":{"r":"HZ-ATH","t":"GLEX","f":"00","desc":"Bombardier Global 6000"},"0022":{"r":"HZ-MS4C","t":"GLF4","f":"00","desc":"Gulfstream Aerospace G450"},"0023":{"r":"HZ-AA","t":"A346","f":"00","desc":"Airbus A340 642X"},"0024":{"r":"HZ-AC","t":"A319","f":"00","desc":"Airbus ACJ319 115XSL"},"0025":{"r":"HZ-BRQ1","t":"B350","f":"00","desc":"Beechcraft Corp King Air B350"},"0028":{"r":"MOI-C1","t":"C295","f":"00","desc":"CASA C-295 W"},"0029":{"r":"HZ-SGA","t":"A320","f":"00","desc":"Airbus A320 232SL"},"002A":{"r":"HZ-ARA","t":"B789","f":"00","desc":"Boeing 787 9"},"002B":{"r":"HZ-ARC","t":"B789","f":"00","desc":"Boeing 787 9"},"002C":{"r":"HZ-ARD","t":"B789","f":"00","desc":"Boeing 787 9"},"002D":{"r":"HZ-SK1","t":"GLF4","f":"00","desc":"Gulfstream Aerospace GIV SP"},"002E":{"r":"HZ-SKY","t":"A346","f":"00","desc":"Airbus A340 642X"},"0030":{"r":"HZ-SK2","t":"GLF4","f":"00","desc":"Gulfstream Aerospace G450"},"0031":{"r":"HZ-SK3","t":"GLF4","f":"00","desc":"Gulfstream Aerospace G450"},"0032":{"r":"HZ-FFG","t":"AT76","f":"00","desc":"Avions de Transport Regional ATR 72 600"},"0033":{"r":"HZ-AKA","t":"B772","f":"00","desc":"Boeing 777 268ER"},"0034":{"r":"HZ-AKB","t":"B772","f":"00","desc":"Boeing 777 268ER"},"0035":{"r":"HZ-AKC","t":"B772","f":"00","desc":"Boeing 777 268ER"},"0036":{"r":"HZ-AKD","t":"B772","f":"00","desc":"Boeing 777 268ER"},"0037":{"r":"HZ-AKE","t":"B772","f":"00","desc":"Boeing 777 268ER"},"0038":{"r":"HZ-AKF","t":"B772","f":"00","desc":"Boeing 777 268ER"},"0039":{"r":"HZ-AKG","t":"B772","f":"00","desc":"Boeing 777 268ER"},"003A":{"r":"HZ-AKH","t":"B772","f":"00","desc":"Boeing 777 268ER"},"003B":{"r":"HZ-AKI","t":"B772","f":"00","desc":"Boeing 777 268ER"},"003C":{"r":"HZ-AKJ","t":"B772","f":"00","desc":"Boeing 777 268ER"},"003D":{"r":"HZ-AKK","t":"B772","f":"00","desc":"Boeing 777 268ER"},"003E":{"r":"HZ-AKL","t":"B772","f":"00","desc":"Boeing 777 268ER"},"003F":{"r":"HZ-AKM","t":"B772","f":"00","desc":"Boeing 777 268ER"},"0040":{"r":"HZ-AKN","t":"B772","f":"00","desc":"Boeing 777 268ER"},"0041":{"r":"HZ-AKO","t":"B772","f":"00","desc":"Boeing 777 268ER"},"0042":{"r":"HZ-AKP","t":"B772","f":"00","desc":"Boeing 777 268ER"},"0043":{"r":"HZ-AKQ","t":"B772","f":"00","desc":"Boeing 777 268ER"},"0044":{"r":"HZ-AKR","t":"B772","f":"00","desc":"Boeing 777 268ER"},"0045":{"r":"HZ-AKS","t":"B772","f":"00","desc":"Boeing 777 268ER"},"0046":{"r":"HZ-AKT","t":"B772","f":"00","desc":"Boeing 777 268ER"},"0047":{"r":"HZ-AKU","t":"B772","f":"00","desc":"Boeing 777 268ER"},"0048":{"r":"HZ-AKV","t":"B772","f":"00","desc":"Boeing 777 268ER"},"0049":{"r":"HZ-AKW","t":"B772","f":"00","desc":"Boeing 777 268ER"},"004A":{"r":"HZ-AQA","t":"A333","f":"00","desc":"Airbus A330 343E"},"004B":{"r":"HZ-AQB","t":"A333","f":"00","desc":"Airbus A330 343E"},"004C":{"r":"HZ-AQC","t":"A333","f":"00","desc":"Airbus A330 343E"},"004D":{"r":"HZ-AQD","t":"A333","f":"00","desc":"Airbus A330 343E"},"004E":{"r":"HZ-AQE","t":"A333","f":"00","desc":"Airbus A330 343E"},"004F":{"r":"HZ-FM2","t":"G300","f":"00","desc":"Gulfstream Aerospace G300"},"0050":{"r":"HZ-AQG","t":"A333","f":"00","desc":"Airbus A330 343E"},"0051":{"r":"HZ-AQH","t":"A333","f":"00","desc":"Airbus A330 343E"},"0052":{"r":"HZ-AQF","t":"A333","f":"00","desc":"Airbus A330 343E"},"0053":{"r":"HZ-AK11","t":"B773","f":"00","desc":"Boeing 777 368ER"},"0054":{"r":"HZ-AK12","t":"B773","f":"00","desc":"Boeing 777 368ER"},"0055":{"r":"HZ-AK13","t":"B773","f":"00","desc":"Boeing 777 368ER"},"0056":{"r":"HZ-AK14","t":"B773","f":"00","desc":"Boeing 777 368ER"},"0057":{"r":"HZ-AK15","t":"B773","f":"00","desc":"Boeing 777 368ER"},"0058":{"r":"HZ-AK16","t":"B773","f":"00","desc":"Boeing 777 368ER"},"0059":{"r":"HZ-AK17","t":"B773","f":"00","desc":"Boeing 777 368ER"},"005A":{"r":"HZ-AK18","t":"B773","f":"00","desc":"Boeing 777 368ER"},"005B":{"r":"HZ-AQI","t":"A333","f":"00","desc":"Airbus A330 343E"},"005C":{"r":"HZ-AQJ","t":"A333","f":"00","desc":"Airbus A330 343E"},"005D":{"r":"HZ-AQK","t":"A333","f":"00","desc":"Airbus A330 343E"},"005E":{"r":"HZ-AK19","t":"B773","f":"00","desc":"Boeing 777 368ER"},"005F":{"r":"HZ-AK20","t":"B773","f":"00","desc":"Boeing 777 368ER"},"0060":{"r":"HZ-AK21","t":"B773","f":"00","desc":"Boeing 777 368ER"},"0061":{"r":"HZ-AK22","t":"B773","f":"00","desc":"Boeing 777 368ER"},"0062":{"r":"HZ-AQL","t":"A333","f":"00","desc":"Airbus A330 343E"},"0063":{"r":"HZ-AK23","t":"B773","f":"00","desc":"Boeing 777 368ER"},"0064":{"r":"HZ-AK24","t":"B773","f":"00","desc":"Boeing 777 368ER"},"006C":{"r":"HZ-AJH","t":"A306","f":"00","desc":""},"006D":{"r":"HZ-AJI","t":"A306","f":"00","desc":""},"006E":{"r":"HZ-AJJ","t":"A306","f":"00","desc":""},"0070":{"r":"HZ-ASA","t":"A320","f":"00","desc":"Airbus A320 214"},"0071":{"r":"HZ-ASB","t":"A320","f":"00","desc":"Airbus A320 214"},"0073":{"r":"HZ-AS11","t":"A320","f":"00","desc":"Airbus A320 214"},"0074":{"r":"HZ-AS12","t":"A320","f":"00","desc":"Airbus A320 214"},"0075":{"r":"HZ-AS13","t":"A320","f":"00","desc":"Airbus A320 214"},"0076":{"r":"HZ-AS14","t":"A320","f":"00","desc":"Airbus A320 214"},"0077":{"r":"HZ-AS15","t":"A320","f":"00","desc":"Airbus A320 214"},"0078":{"r":"HZ-AS16","t":"A320","f":"00","desc":"Airbus A320 214"},"007A":{"r":"HZ-AS31","t":"A320","f":"00","desc":"Airbus A320 214"},"007B":{"r":"HZ-AS32","t":"A320","f":"00","desc":"Airbus A320 214"},"007C":{"r":"HZ-ASC","t":"A320","f":"00","desc":"Airbus A320 214"},"007D":{"r":"HZ-AS33","t":"A320","f":"00","desc":"Airbus A320 214"},"007E":{"r":"HZ-ASD","t":"A320","f":"00","desc":"Airbus A320 214"},"007F":{"r":"HZ-ASE","t":"A320","f":"00","desc":"Airbus A320 214"},"0080":{"r":"HZ-AS18","t":"A320","f":"00","desc":"Airbus A320 214"},"0081":{"r":"HZ-AS19","t":"A320","f":"00","desc":"Airbus A320 214"},"0082":{"r":"HZ-AS34","t":"A320","f":"00","desc":"Airbus A320 214"},"0083":{"r":"HZ-AS35","t":"A320","f":"00","desc":"Airbus A320 214"},"0084":{"r":"HZ-AS36","t":"A320","f":"00","desc":"Airbus A320 214"},"0085":{"r":"HZ-AS17","t":"A320","f":"00","desc":"Airbus A320 214"},"0086":{"r":"HZ-AS20","t":"A320","f":"00","desc":"Airbus A320 214"},"0087":{"r":"HZ-AS21","t":"A320","f":"00","desc":"Airbus A320 214"},"0088":{"r":"HZ-AS37","t":"A320","f":"00","desc":"Airbus A320 214"},"0089":{"r":"HZ-AS38","t":"A320","f":"00","desc":"Airbus A320 214"},"008A":{"r":"HZ-AS22","t":"A320","f":"00","desc":"Airbus A320 214"},"008B":{"r":"HZ-AS39","t":"A320","f":"00","desc":"Airbus A320 214"},"008C":{"r":"HZ-AS40","t":"A320","f":"00","desc":"Airbus A320 214"},"008D":{"r":"HZ-AS41","t":"A320","f":"00","desc":"Airbus A320 214"},"008E":{"r":"HZ-AS42","t":"A320","f":"00","desc":"Airbus A320 214"},"008F":{"r":"HZ-AS43","t":"A320","f":"00","desc":"Airbus A320 214"},"0090":{"r":"HZ-ASH","t":"A321","f":"00","desc":"Airbus A321 211"},"0091":{"r":"HZ-ASI","t":"A321","f":"00","desc":"Airbus A321 211"},"0092":{"r":"HZ-ASJ","t":"A321","f":"00","desc":"Airbus A321 211"},"0093":{"r":"HZ-ASK","t":"A321","f":"00","desc":"Airbus A321 211"},"0094":{"r":"HZ-AS44","t":"A320","f":"00","desc":"Airbus A320 214"},"0095":{"r":"HZ-AS23","t":"A320","f":"00","desc":"Airbus A320 214"},"0096":{"r":"HZ-AS45","t":"A320","f":"00","desc":"Airbus A320 214"},"0097":{"r":"HZ-AEA","t":"E170","f":"00","desc":"Embraer EMB-170 LR"},"0098":{"r":"HZ-AEB","t":"E170","f":"00","desc":"Embraer EMB-170 LR"},"0099":{"r":"HZ-AEC","t":"E170","f":"00","desc":"Embraer EMB-170 LR"},"009A":{"r":"HZ-AED","t":"E170","f":"00","desc":"Embraer EMB-170 LR"},"009B":{"r":"HZ-AEE","t":"E170","f":"00","desc":"Embraer EMB-170 LR"},"009C":{"r":"HZ-AEF","t":"E170","f":"00","desc":"Embraer EMB-170 LR"},"009D":{"r":"HZ-AEG","t":"E170","f":"00","desc":"Embraer EMB-170 LR"},"009F":{"r":"HZ-AEI","t":"E170","f":"00","desc":"Embraer EMB-170 LR"},"00A0":{"r":"HZ-AEJ","t":"E170","f":"00","desc":"Embraer EMB-170 LR"},"00A1":{"r":"HZ-AEK","t":"E170","f":"00","desc":"Embraer EMB-170 LR"},"00A2":{"r":"HZ-AEL","t":"E170","f":"00","desc":"Embraer EMB-170 LR"},"00A3":{"r":"HZ-AEM","t":"E170","f":"00","desc":"Embraer EMB-170 LR"},"00A4":{"r":"HZ-AEN","t":"E170","f":"00","desc":"Embraer EMB-170 LR"},"00A5":{"r":"HZ-AEO","t":"E170","f":"00","desc":"Embraer EMB-170 LR"},"00A6":{"r":"HZ-ASF","t":"A320","f":"00","desc":"Airbus A320 214"},"00A7":{"r":"HZ-ASL","t":"A321","f":"00","desc":"Airbus A321 211"},"00A8":{"r":"HZ-ASM","t":"A321","f":"00","desc":"Airbus A321 211"},"00A9":{"r":"HZ-ASN","t":"A321","f":"00","desc":"Airbus A321 211"},"00AA":{"r":"HZ-ASP","t":"A321","f":"00","desc":"Airbus A321 211"},"00AB":{"r":"HZ-ASO","t":"A321","f":"00","desc":"Airbus A321 211"},"00AC":{"r":"HZ-ASQ","t":"A321","f":"00","desc":"Airbus A321 211"},"00AD":{"r":"HZ-ASG","t":"A320","f":"00","desc":"Airbus A320 214"},"00AE":{"r":"HZ-ASR","t":"A321","f":"00","desc":"Airbus A321 231"},"00AF":{"r":"HZ-AST","t":"A321","f":"00","desc":"Airbus A321 211"},"00B0":{"r":"HZ-ASU","t":"A321","f":"00","desc":"Airbus A321 211"},"00B1":{"r":"HZ-ASW","t":"A321","f":"00","desc":"Airbus A321 211"},"00B2":{"r":"HZ-ASV","t":"A321","f":"00","desc":"Airbus A321 211"},"00B3":{"r":"HZ-AK25","t":"B773","f":"00","desc":"Boeing 777 368ER"},"00B4":{"r":"HZ-ARB","t":"B789","f":"00","desc":"Boeing 787 9"},"00B5":{"r":"HZ-AQ11","t":"A333","f":"00","desc":"Airbus A330 343E"},"00B6":{"r":"HZ-AQ12","t":"A333","f":"00","desc":"Airbus A330 343E"},"00B7":{"r":"HZ-AQ13","t":"A333","f":"00","desc":"Airbus A330 343E"},"00B8":{"r":"HZ-AQ14","t":"A333","f":"00","desc":"Airbus A330 343E"},"00B9":{"r":"HZ-AQ15","t":"A333","f":"00","desc":"Airbus A330 343E"},"00BA":{"r":"HZ-AQ16","t":"A333","f":"00","desc":"Airbus A330 343E"},"00BB":{"r":"HZ-AQ17","t":"A333","f":"00","desc":"Airbus A330 343E"},"00BC":{"r":"HZ-AQ18","t":"A333","f":"00","desc":"Airbus A330 343E"},"00BD":{"r":"HZ-AQ19","t":"A333","f":"00","desc":"Airbus A330 343E"},"00BE":{"r":"HZ-AQ20","t":"A333","f":"00","desc":"Airbus A330 343E"},"00BF":{"r":"HZ-AK31","t":"B773","f":"00","desc":"Boeing 777 3FGER"},"00C0":{"r":"HZ-AK32","t":"B77W","f":"00","desc":"777-3FGER"},"00C1":{"r":"HZ-AK33","t":"B77W","f":"00","desc":"777-3FGER"},"00C2":{"r":"HZ-AK34","t":"B77W","f":"00","desc":"777-3FGER"},"00C3":{"r":"HZ-AK35","t":"B77W","f":"00","desc":"777-3FGER"},"00C4":{"r":"HZ-MHH","t":"AT76","f":"00","desc":"Avions de Transport Regional ATR 72 600"},"00C5":{"r":"HZ-SK11","t":"E550","f":"00","desc":"Embraer Legacy 500"},"00C6":{"r":"HZ-SK12","t":"E55P","f":"00","desc":"Embraer Phenom 300"},"00C7":{"r":"HZ-SK4","t":"GLF5","f":"00","desc":"Gulfstream Aerospace GV"},"00C8":{"r":"HZ-AK36","t":"B77W","f":"00","desc":"777-3FGER"},"00C9":{"r":"HZ-APA","t":"MD90","f":"00","desc":""},"00CA":{"r":"HZ-APB","t":"MD90","f":"00","desc":""},"00CB":{"r":"HZ-APC","t":"MD90","f":"00","desc":""},"00CC":{"r":"HZ-APD","t":"MD90","f":"00","desc":""},"00CD":{"r":"HZ-APE","t":"MD90","f":"00","desc":""},"00CE":{"r":"HZ-APF","t":"MD90","f":"00","desc":""},"00CF":{"r":"HZ-APG","t":"MD90","f":"00","desc":""},"00D0":{"r":"HZ-APH","t":"MD90","f":"00","desc":""},"00D1":{"r":"HZ-API","t":"MD90","f":"00","desc":""},"00D2":{"r":"HZ-APJ","t":"MD90","f":"00","desc":""},"00D3":{"r":"HZ-APK","t":"MD90","f":"00","desc":""},"00D4":{"r":"HZ-APL","t":"MD90","f":"00","desc":""},"00D5":{"r":"HZ-APM","t":"MD90","f":"00","desc":"McDonnell Douglas MD-90 30"},"00D6":{"r":"HZ-APN","t":"MD90","f":"00","desc":""},"00D7":{"r":"HZ-APO","t":"MD90","f":"00","desc":""},"00D8":{"r":"HZ-APP","t":"MD90","f":"00","desc":""},"00D9":{"r":"HZ-APQ","t":"MD90","f":"00","desc":""},"00DA":{"r":"HZ-APR","t":"MD90","f":"00","desc":""},"00DB":{"r":"HZ-APS","t":"MD90","f":"00","desc":""},"00DC":{"r":"HZ-APT","t":"MD90","f":"00","desc":""},"00DD":{"r":"HZ-APU","t":"MD90","f":"00","desc":"McDonnell Douglas MD-90 30"},"00DE":{"r":"HZ-APV","t":"MD90","f":"00","desc":""},"00DF":{"r":"HZ-APW","t":"MD90","f":"00","desc":""},"00E0":{"r":"HZ-APX","t":"MD83","f":"00","desc":""},"00E1":{"r":"HZ-APY","t":"MD90","f":"00","desc":""},"00E2":{"r":"HZ-APZ","t":"MD90","f":"00","desc":"McDonnell Douglas MD-90 30"},"00E3":{"r":"HZ-AP7","t":"MD90","f":"00","desc":""},"00E4":{"r":"HZ-AP3","t":"MD90","f":"00","desc":""},"00E5":{"r":"HZ-AP4","t":"MD90","f":"00","desc":""},"00E6":{"r":"HZ-SPAC","t":"BE40","f":"00","desc":"Hawker Beechcraft Corp Hawker 400XP"},"00E7":{"r":"HZ-SPAG","t":"FA7X","f":"00","desc":"Dassault Falcon 7X"},"00E8":{"r":"HZ-SPAB","t":"BE40","f":"00","desc":"Hawker Beechcraft Corp Hawker 400XP"},"00E9":{"r":"HZ-SPAA","t":"BE40","f":"00","desc":"Hawker Beechcraft Corp Hawker 400XP"},"00EA":{"r":"HZ-SPAD","t":"BE40","f":"00","desc":"Hawker Beechcraft Corp Hawker 400XP"},"00EB":{"r":"HZ-SPAE","t":"BE40","f":"00","desc":"Hawker Beechcraft Corp Hawker 400XP"},"00EC":{"r":"HZ-SPAH","t":"FA7X","f":"00","desc":"Dassault Falcon 7X"},"00ED":{"r":"HZ-SPAF","t":"BE40","f":"00","desc":"Hawker Beechcraft Corp Hawker 400XP"},"00EE":{"r":"HZ-SPAI","t":"FA7X","f":"00","desc":"Dassault Falcon 7X"},"00EF":{"r":"HZ-SPAL","t":"F900","f":"00","desc":""},"00F0":{"r":"HZ-SPAJ","t":"FA7X","f":"00","desc":"Dassault Falcon 7X"},"00F2":{"r":"HZ-SAE","t":"DA40","f":"00","desc":"Diamond Aircraft Diamond Star DA40 NG"},"00F3":{"r":"HZ-HR5","t":"B738","f":"00","desc":"Boeing 737NG 8AN\/W BBJ2"},"00F5":{"r":"HZ-FM1","t":"B735","f":"00","desc":"Boeing 737 528"},"00FA":{"r":"HZ-A11","t":"AT76","f":"00","desc":"Avions de Transport Regional ATR 72 600"},"00FE":{"r":"HZ-IAM","t":"E35L","f":"00","desc":"Embraer Legacy 600"},"0100":{"r":"HZ-AK71","t":"B77L","f":"00","desc":"Boeing 777 FFG"},"0101":{"r":"HZ-AK72","t":"B77L","f":"00","desc":"Boeing 777 FFG"},"0102":{"r":"HZ-AK73","t":"B77L","f":"00","desc":"Boeing 777 FFG"},"0103":{"r":"HZ-AK74","t":"B77L","f":"00","desc":"Boeing 777 FFG"},"0104":{"r":"HZ-AK26","t":"B773","f":"00","desc":"Boeing 777 368ER"},"0105":{"r":"HZ-AK27","t":"B773","f":"00","desc":"Boeing 777 368ER"},"0106":{"r":"HZ-AK28","t":"B773","f":"00","desc":"Boeing 777 368ER"},"0107":{"r":"HZ-AK29","t":"B773","f":"00","desc":"Boeing 777 368ER"},"0108":{"r":"HZ-AK30","t":"B773","f":"00","desc":"Boeing 777 368ER"},"010A":{"r":"HZ-103","t":"GLF4","f":"10","desc":"Gulfstream Aerospace GIV"},"010B":{"r":"HZ-124","t":"A342","f":"10","desc":"Airbus A340 213"},"010F":{"r":"HZ-AK37","t":"B773","f":"00","desc":"Boeing 777 3FGER"},"0110":{"r":"HZ-AK38","t":"B773","f":"00","desc":"Boeing 777 3FGER"},"0111":{"r":"HZ-AK39","t":"B773","f":"00","desc":"Boeing 777 3FGER"},"0112":{"r":"HZ-AK40","t":"B773","f":"00","desc":"Boeing 777 3FGER"},"0113":{"r":"HZ-AS51","t":"A320","f":"00","desc":"Airbus A320 214SL"},"0114":{"r":"HZ-AS52","t":"A320","f":"00","desc":"Airbus A320 214SL"},"0115":{"r":"HZ-AS53","t":"A320","f":"00","desc":"Airbus A320 214SL"},"0116":{"r":"HZ-AS54","t":"A320","f":"00","desc":"Airbus A320 214SL"},"0117":{"r":"HZ-AS55","t":"A320","f":"00","desc":"Airbus A320 214SL"},"0119":{"r":"HZ-AK41","t":"B773","f":"01","desc":"777 300ER"},"018A":{"r":"HZ-AQ23","t":"A333","f":"00","desc":"Airbus A330 343E"},"018C":{"r":"HZ-AQ21","t":"A333","f":"00","desc":"Airbus A330 343E"},"0191":{"r":"HZ-ANA","t":"MD11","f":"00","desc":"McDonnell Douglas MD-11 F"},"0192":{"r":"HZ-ANB","t":"MD11","f":"00","desc":"McDonnell Douglas MD-11 F"},"0193":{"r":"HZ-ANC","t":"MD11","f":"00","desc":"McDonnell Douglas MD-11 F"},"0194":{"r":"HZ-AND","t":"MD11","f":"00","desc":"McDonnell Douglas MD-11 F"},"0196":{"r":"HZ-MS51","t":"A139","f":"00","desc":"AgustaWestland AW.139"},"0197":{"r":"HZ-MS52","t":"A139","f":"00","desc":"AgustaWestland AW.139"},"01A1":{"r":"HZ-MS4A","t":"GLF4","f":"10","desc":"Gulfstream Aerospace G450"},"01B2":{"r":"HZ-HR3","t":"B722","f":"00","desc":""},"01BA":{"r":"HZ-AB3","t":"B722","f":"00","desc":"Boeing 727 2U5\/W"},"01C0":{"r":"HZ-AFA2","t":"CL60","f":"00","desc":""},"01C3":{"r":"HZ-SJP3","t":"CL60","f":"00","desc":""},"01C7":{"r":"HZ-AFT","t":"F900","f":"00","desc":"Dassault Falcon 900"},"01C8":{"r":"HZ-AFN","t":"GLF3","f":"00","desc":"G-1159A"},"01CC":{"r":"HZ-AFR","t":"GLF3","f":"00","desc":"Grumman GIII"},"01CD":{"r":"HZ-AFV","t":"GLF4","f":"00","desc":"Gulfstream Aerospace GIV"},"01CE":{"r":"HZ-AFZ","t":"F900","f":"00","desc":"Dassault Falcon 900 B"},"01D1":{"r":"HZ-AFU","t":"GLF4","f":"00","desc":"Gulfstream Aerospace GIV"},"01D2":{"r":"HZ-AFX","t":"GLF4","f":"00","desc":"Gulfstream Aerospace GIV"},"01D3":{"r":"HZ-KSDC","t":"F2TH","f":"00","desc":"Dassault Falcon 2000"},"01D4":{"r":"HZ-AFA","t":"CL60","f":"00","desc":""},"01D5":{"r":"HZ-AFW","t":"GLF4","f":"00","desc":"Gulfstream Aerospace GIV"},"01D6":{"r":"HZ-MS3","t":"GLF3","f":"00","desc":""},"01D9":{"r":"N105AJ","t":"GLF2","f":"00","desc":""},"01DA":{"r":"HZ-RC3","t":"GLF3","f":"00","desc":"Grumman GIII"},"01E0":{"r":"HZ-MS5A","t":"GLF5","f":"10","desc":"Gulfstream Aerospace GV"},"01E2":{"r":"HZ-MF1","t":"B737","f":"00","desc":"Boeing 737NG 7FG\/W BBJ"},"01E3":{"r":"HZ-MF2","t":"B737","f":"00","desc":"Boeing 737NG 7AJ\/W BBJ"},"01E4":{"r":"HZ-WBT5","t":"H25B","f":"00","desc":"British Aerospace 125 800A"},"01E6":{"r":"HZ-NSA","t":"A310","f":"00","desc":"Airbus A310 304"},"01E7":{"r":"HZ-MF3","t":"G300","f":"00","desc":"Gulfstream Aerospace G300"},"01E8":{"r":"HZ-SNA","t":"B722","f":"00","desc":""},"01E9":{"r":"HZ-MF4","t":"G300","f":"00","desc":"Gulfstream Aerospace G300"},"01EA":{"r":"HZ-SNB","t":"B722","f":"00","desc":"Boeing 727 223F"},"01EB":{"r":"HZ-SNC","t":"B722","f":"00","desc":""},"01EC":{"r":"HZ-SND","t":"B722","f":"00","desc":"Boeing 727-223F"},"01EE":{"r":"HZ-SN10","t":"SW4","f":"00","desc":""},"01EF":{"r":"HZ-XY7","t":"A320","f":"00","desc":"A320-200"},"01F0":{"r":"HZ-MF5","t":"G300","f":"00","desc":"Gulfstream Aerospace G300"},"01F1":{"r":"HZ-WBT7","t":"B744","f":"01","desc":"Boeing 747 4J6"},"01F2":{"r":"HZ-ARK","t":"GLF5","f":"00","desc":"Gulfstream Aerospace G550"},"01F3":{"r":"HZ-SKI","t":"B722","f":"00","desc":"Boeing 727 212\/W"},"01F4":{"r":"HZ-BL1","t":"C525","f":"00","desc":"Cessna Citation CJ1"},"01F8":{"r":"HZ-OFC5","t":"F900","f":"00","desc":""},"01FC":{"r":"HZ-DME","t":"F900","f":"00","desc":"Dassault Falcon 900"},"01FD":{"r":"HZ-NMA","t":"B733","f":"00","desc":""},"0200":{"r":"HZ-BIN","t":"H25B","f":"00","desc":"Hawker Beechcraft Corp Hawker 900XP"},"0203":{"r":"HZ-KSGA","t":"GLF4","f":"00","desc":"Gulfstream Aerospace G450"},"0204":{"r":"HZ-MS71","t":"B350","f":"00","desc":"Hawker Beechcraft Corp King Air 350C"},"0205":{"r":"HZ-MS72","t":"B350","f":"00","desc":"Hawker Beechcraft Corp King Air 350C"},"0209":{"r":"HZ-MS74","t":"B350","f":"00","desc":"Hawker Beechcraft Corp King Air 350C"},"020A":{"r":"HZ-MS75","t":"B350","f":"00","desc":"Hawker Beechcraft Corp King Air 350C"},"020B":{"r":"HZ-KSRD","t":"H25B","f":"00","desc":"Hawker Beechcraft Corp Hawker 750"},"0217":{"r":"HZ-AJ2","t":"A320","f":"00","desc":""},"0218":{"r":"HZ-AJ3","t":"A320","f":"00","desc":""},"021A":{"r":"HZ-AWA1","t":"B744","f":"00","desc":""},"021B":{"r":"HZ-AWA3","t":"B744","f":"00","desc":""},"021C":{"r":"HZ-AWA2","t":"B744","f":"00","desc":""},"021D":{"r":"HZ-MS1A","t":"LJ60","f":"00","desc":"Bombardier Learjet 60 XR"},"021E":{"r":"HZ-MS1B","t":"LJ60","f":"00","desc":"Bombardier Learjet 60 XR"},"021F":{"r":"HZ-BSA","t":"C56X","f":"00","desc":""},"0220":{"r":"HZ-ALFA","t":"GLF5","f":"00","desc":""},"0221":{"r":"HZ-HHT","t":"GLF3","f":"00","desc":"Grumman GIII"},"0222":{"r":"HZ-ATR","t":"B739","f":"00","desc":"Boeing 737NG 9FGER BBJ"},"0223":{"r":"HZ-SKY3","t":"A320","f":"00","desc":"Airbus ACJ320 214X"},"0226":{"r":"HZ-A4","t":"A319","f":"00","desc":"Airbus A319 112"},"0227":{"r":"HZ-RCA","t":"A318","f":"00","desc":"Airbus ACJ318 112 Elite"},"0228":{"r":"HZ-A8","t":"H25B","f":"00","desc":"Hawker Beechcraft Corp Hawker 900XP"},"0229":{"r":"HZ-MKG","t":"GLF4","f":"00","desc":""},"022A":{"r":"HZ-OFC6","t":"FA7X","f":"00","desc":""},"022B":{"r":"HZ-MF6","t":"B739","f":"01","desc":"Boeing 737NG 9FG\/W"},"022E":{"r":"HZ-A3","t":"A320","f":"00","desc":"Airbus A320 214"},"022F":{"r":"HZ-SA01","t":"DA40","f":"00","desc":"Diamond Aircraft Diamond Star DA40 NG"},"0230":{"r":"HZ-SA02","t":"DA40","f":"00","desc":"Diamond Aircraft Diamond Star DA40 NG"},"0237":{"r":"HZ-KME1","t":"C56X","f":"00","desc":"Cessna Citation XLS"},"0238":{"r":"HZ-A9","t":"H25B","f":"00","desc":"Hawker Beechcraft Corp Hawker 900XP"},"023F":{"r":"HZ-HSH","t":"CL60","f":"00","desc":"Bombardier Challenger 604"},"0240":{"r":"HZ-IBN","t":"E55P","f":"00","desc":""},"0243":{"r":"HZ-NGN","t":"LJ60","f":"00","desc":""},"0245":{"r":"HZ-SA18","t":"DA42","f":"00","desc":"Diamond Aircraft Twin Star DA42 NG"},"0246":{"r":"HZ-SSM","t":"B350","f":"00","desc":"Beech King Air B350"},"0247":{"r":"HZ-A5","t":"A318","f":"00","desc":"Airbus ACJ318 112 Elite"},"0248":{"r":"HZ-MEJ1","t":"CL60","f":"00","desc":"Bombardier Challenger 604"},"0249":{"r":"HZ-NJ1","t":"C172","f":"00","desc":"Cessna 172S Skyhawk SP"},"024E":{"r":"HZ-OHS","t":"CL60","f":"00","desc":"Bombardier Challenger 601 3A"},"024F":{"r":"HZ-HAA","t":"B735","f":"00","desc":"Boeing 737 529\/W"},"0250":{"r":"HZ-SA17","t":"DA42","f":"00","desc":"Diamond Aircraft Twin Star DA42 NG"},"0251":{"r":"HZ-A10","t":"AT46","f":"00","desc":"Avions de Transport Regional ATR 42 600"},"0254":{"r":"HZ-SK6","t":"GLF5","f":"00","desc":"Gulfstream Aerospace G550"},"0258":{"r":"HZ-ATG","t":"CL60","f":"10","desc":"Bombardier Challenger 605"},"0259":{"r":"1630","t":"C130","f":"10","desc":"Lockheed C-130H-30 Hercules"},"025A":{"r":"472","t":"C130","f":"10","desc":"Lockheed C-130H Hercules"},"025B":{"r":"473","t":"C130","f":"10","desc":"Lockheed C-130H Hercules"},"025C":{"r":"1622","t":"C130","f":"10","desc":"Lockheed C-130H-30 Hercules"},"025D":{"r":"1623","t":"C130","f":"10","desc":"Lockheed C-130H Hercules"},"025E":{"r":"1624","t":"C130","f":"10","desc":"Lockheed C-130H Hercules"},"0261":{"r":"703","t":"TOR","f":"10","desc":"Panavia Tornado IDS"},"026B":{"r":"767","t":"TOR","f":"10","desc":"Panavia Tornado IDS"},"0274":{"r":"6606","t":"TOR","f":"00","desc":"Panavia Tornado IDS"},"0278":{"r":"6611","t":"TOR","f":"00","desc":"Panavia Tornado IDS"},"0282":{"r":"6622","t":"TOR","f":"10","desc":"Panavia Tornado IDS(T)"},"0284":{"r":"6624","t":"TOR","f":"10","desc":"Panavia Tornado IDS(T)"},"0285":{"r":"6625","t":"TOR","f":"10","desc":"Panavia Tornado IDS(T)"},"028B":{"r":"6631","t":"TOR","f":"10","desc":"Panavia Tornado IDS(R)"},"028E":{"r":"6634","t":"TOR","f":"10","desc":"Panavia Tornado IDS(R)"},"028F":{"r":"7501","t":"TOR","f":"10","desc":"Panavia Tornado IDS(T)"},"0290":{"r":"7502","t":"TOR","f":"10","desc":"Panavia Tornado IDS(T)"},"0291":{"r":"7503","t":"TOR","f":"10","desc":"Panavia Tornado IDS(T)"},"0292":{"r":"7504","t":"TOR","f":"10","desc":"Panavia Tornado IDS"},"02A1":{"r":"8302","t":"TOR","f":"00","desc":"Panavia Tornado IDS(T)"},"02B0":{"r":"8317","t":"TOR","f":"00","desc":"Panavia Tornado IDS"},"02C3":{"r":"HZ-111","t":"C130","f":"00","desc":"Lockheed VC-130H Hercules"},"02C4":{"r":"HZ-112","t":"C130","f":"00","desc":"Lockheed VC-130H Hercules"},"02DC":{"r":"482","t":"C130","f":"00","desc":"Lockheed C-130H Hercules"},"02DD":{"r":"483","t":"C130","f":"00","desc":"Lockheed C-130H Hercules"},"02DE":{"r":"1632","t":"C130","f":"00","desc":"Lockheed C-130H Hercules"},"02E0":{"r":"1631","t":"C130","f":"00","desc":"Lockheed C-130H-30 Hercules"},"02E1":{"r":"474","t":"C130","f":"10","desc":"Lockheed C-130H Hercules"},"02E3":{"r":"1625","t":"C130","f":"00","desc":"Lockheed C-130H Hercules"},"02E4":{"r":"1626","t":"C130","f":"10","desc":"Lockheed C-130H Hercules"},"02F9":{"r":"2401","t":"A332","f":"10","desc":"Airbus A330 202MRTT"},"02FC":{"r":"2404","t":"A332","f":"00","desc":"Airbus A330 202MRTT"},"02FD":{"r":"2405","t":"A332","f":"00","desc":"Airbus A330 202MRTT"},"02FE":{"r":"2406","t":"A332","f":"00","desc":"Airbus A330 202MRTT"},"0321":{"r":"HZ-HM1A","t":"B743","f":"00","desc":"Boeing 747 3G1"},"0322":{"r":"HZ-HM1B","t":"B74S","f":"00","desc":"Boeing 747 SP68"},"0323":{"r":"HZ-AIJ","t":"B74S","f":"00","desc":""},"032C":{"r":"HZ-HMED","t":"B752","f":"00","desc":"Boeing 757 23A"},"032E":{"r":"HZ-HM7","t":"MD11","f":"00","desc":"McDonnell Douglas MD-11 P"},"0330":{"r":"HZ-HMS","t":"A342","f":"00","desc":""},"0331":{"r":"HZ-AFAS","t":"MD11","f":"00","desc":""},"0333":{"r":"HZ-HM1","t":"B744","f":"00","desc":"Boeing 747 468"},"0334":{"r":"HZ-HMS2","t":"A342","f":"00","desc":"Airbus A340 213X"},"0336":{"r":"HZ-HM1C","t":"B74S","f":"00","desc":"Boeing 747 SP68"},"0368":{"r":"2101","t":"HAWK","f":"10","desc":"Hawker Siddeley Hawk T.1A"},"0369":{"r":"2102","t":"HAWK","f":"10","desc":"Hawker Siddeley Hawk T.1A"},"036A":{"r":"2103","t":"HAWK","f":"10","desc":"Hawker Siddeley Hawk T.1A"},"036B":{"r":"2104","t":"HAWK","f":"10","desc":"Hawker Siddeley Hawk T.1A"},"036C":{"r":"2105","t":"HAWK","f":"10","desc":"Hawker Siddeley Hawk T.1A"},"036D":{"r":"2106","t":"HAWK","f":"10","desc":"Hawker Siddeley Hawk T.1A"},"036E":{"r":"2107","t":"HAWK","f":"10","desc":"Hawker Siddeley Hawk T.1A"},"036F":{"r":"2108","t":"HAWK","f":"10","desc":"Hawker Siddeley Hawk T.1A"},"0370":{"r":"2109","t":"HAWK","f":"10","desc":"Hawker Siddeley Hawk T.1A"},"0373":{"r":"2110","t":"HAWK","f":"10","desc":"Hawker Siddeley Hawk T.1A"},"0374":{"r":"2111","t":"HAWK","f":"10","desc":"Hawker Siddeley Hawk T.1A"},"0375":{"r":"2112","t":"HAWK","f":"10","desc":"Hawker Siddeley Hawk T.1A"},"0376":{"r":"2113","t":"HAWK","f":"10","desc":"Hawker Siddeley Hawk T.1A"},"0377":{"r":"ZB114","t":"HAWK","f":"00","desc":"British Aerospace Hawk Mk.165"},"0378":{"r":"ZB115","t":"HAWK","f":"00","desc":"British Aerospace Hawk Mk.165"},"0379":{"r":"ZB118","t":"HAWK","f":"00","desc":"British Aerospace Hawk Mk.165"},"037A":{"r":"ZB119","t":"HAWK","f":"00","desc":"British Aerospace Hawk Mk.165"},"0385":{"r":"486","t":"C130","f":"10","desc":"Lockheed VC-130H Hercules"},"0386":{"r":"HZ-128","t":"C130","f":"10","desc":"Lockheed L-100-30 Hercules"},"0387":{"r":"HZ-129","t":"C130","f":"00","desc":"Lockheed L-100-30 Hercules"},"0388":{"r":"485","t":"C130","f":"10","desc":"Lockheed C-130H Hercules"},"038A":{"r":"HZ-105","t":"H25B","f":"00","desc":"British Aerospace 125 800B"},"038C":{"r":"HZ-109","t":"H25B","f":"00","desc":"British Aerospace 125 800B"},"038D":{"r":"HZ-110","t":"H25B","f":"00","desc":"British Aerospace 125 800B"},"038E":{"r":"HZ-130","t":"H25B","f":"10","desc":"British Aerospace 125 800B"},"038F":{"r":"HZ-132","t":"C130","f":"10","desc":"Lockheed L-100-30 Hercules"},"0391":{"r":"HZ-101","t":"B737","f":"10","desc":"Boeing 737NG 7DP\/W BBJ"},"0392":{"r":"HZ-102","t":"B738","f":"10","desc":"Boeing 737NG 8DP\/W BBJ2"},"0393":{"r":"HZ-133","t":"C55B","f":"10","desc":"Cessna Citation Bravo"},"0394":{"r":"HZ-134","t":"C55B","f":"10","desc":"Cessna Citation Bravo"},"0396":{"r":"HZ-136","t":"C55B","f":"10","desc":"Cessna Citation Bravo"},"03A9":{"r":"4103","t":"B350","f":"00","desc":"Hawker Beechcraft Corp King Air B350"},"03AA":{"r":"5001","t":"B350","f":"00","desc":"Beechcraft Corp King Air B350"},"03AB":{"r":"5002","t":"B350","f":"10","desc":"Beechcraft Corp King Air B350"},"03AC":{"r":"5003","t":"B350","f":"00","desc":"Beechcraft Corp King Air B350"},"03AD":{"r":"5004","t":"B350","f":"00","desc":"Beechcraft Corp King Air B350"},"03AE":{"r":"5005","t":"B350","f":"00","desc":"Beechcraft Corp King Air B350"},"03AF":{"r":"5006","t":"B350","f":"00","desc":"Beechcraft Corp King Air B350"},"03B0":{"r":"5007","t":"B350","f":"00","desc":"Beechcraft Corp King Air B350"},"03B1":{"r":"5008","t":"B350","f":"00","desc":"B300 King Air 350"},"03B2":{"r":"5009","t":"B350","f":"00","desc":"Beechcraft Corp King Air B350"},"03B6":{"r":"4107","t":"B350","f":"01","desc":"King Air 350"},"03B9":{"r":"HZ-SKY1","t":"A342","f":"00","desc":"Airbus A340 212"},"03BA":{"r":"HZ-SK5","t":"GLF4","f":"00","desc":"Gulfstream Aerospace G450"},"03BB":{"r":"HZ-A15","t":"A320","f":"00","desc":"Airbus A320 216"},"03D5":{"r":"3209","t":"C30J","f":"00","desc":"Lockheed KC-130J Hercules"},"03E8":{"r":"HZ-MS4B","t":"GLF4","f":"01","desc":"Gulfstream Aerospace G450"},"03E9":{"r":"HZ-MFL","t":"GLF4","f":"00","desc":"Gulfstream Aerospace GIV"},"03EB":{"r":"HZ-AFY","t":"GLF4","f":"00","desc":"Gulfstream Aerospace GIV"},"03EE":{"r":"HZ-TAA","t":"B737","f":"00","desc":""},"03F0":{"r":"HZ-HA1","t":"GLF2","f":"00","desc":"Grumman GII TT"},"03F2":{"r":"HZ-MS4","t":"GLF4","f":"00","desc":"Gulfstream Aerospace GIV SP"},"03F6":{"r":"HZ-OFC4","t":"F900","f":"00","desc":""},"03FA":{"r":"HZ-MIS","t":"B732","f":"00","desc":""},"03FB":{"r":"HZ-FYZ","t":"C56X","f":"00","desc":""},"03FE":{"r":"HZ-KSRC","t":"H25B","f":"00","desc":"Raytheon Aircraft Company 125 800XP"},"8874":{"r":"HL1074","t":"C172","f":"00","desc":"Cessna 172Q Cutlass"},"8883":{"r":"HL1083","t":"C172","f":"00","desc":"Cessna 172S Skyhawk SP"},"8884":{"r":"HL1084","t":"C172","f":"00","desc":"Cessna 172S Skyhawk SP"},"8895":{"r":"HL1095","t":"C172","f":"00","desc":"Cessna 172S Skyhawk SP"},"8909":{"r":"HL1109","t":"C172","f":"00","desc":"Cessna 172S Skyhawk SP"},"8924":{"r":"HL1124","t":"C172","f":"00","desc":"Cessna 172S Skyhawk SP"},"8925":{"r":"HL1125","t":"C172","f":"00","desc":"Cessna 172S Skyhawk SP"},"8926":{"r":"HL1126","t":"C172","f":"00","desc":"Cessna 172S Skyhawk SP"},"8928":{"r":"HL1128","t":"C172","f":"00","desc":"Cessna 172S Skyhawk SP"},"8943":{"r":"HL1143","t":"C172","f":"00","desc":"Cessna 172S Skyhawk SP"},"8952":{"r":"HL1152","t":"C172","f":"00","desc":"Cessna 172S Skyhawk SP"},"8969":{"r":"HL1169","t":"C172","f":"00","desc":"Cessna 172S Skyhawk SP"},"8970":{"r":"HL1170","t":"C172","f":"00","desc":"Cessna 172S Skyhawk SP"},"8974":{"r":"HL1174","t":"C172","f":"00","desc":"Cessna 172S Skyhawk SP"},"8998":{"r":"HL1198","t":"C172","f":"00","desc":"Cessna 172S Skyhawk SP"},"9032":{"r":"HL2032","t":"PA44","f":"00","desc":"Piper PA-44 180 Seminole"},"9040":{"r":"HL2040","t":"DA42","f":"00","desc":"Diamond Aircraft Twin Star DA42"},"BA22":{"r":"HL7222","t":"GLF4","f":"00","desc":""},"BA27":{"r":"HL7227","t":"B737","f":"00","desc":"Boeing 737NG 7HF\/W BBJ"},"BA39":{"r":"HL7239","t":"A306","f":"00","desc":""},"BA41":{"r":"HL7241","t":"A306","f":"00","desc":""},"BA42":{"r":"HL7242","t":"A306","f":"00","desc":""},"BA47":{"r":"HL7247","t":"B763","f":"00","desc":"Boeing 767 38E"},"BA48":{"r":"HL7248","t":"B763","f":"00","desc":"Boeing 767 38E"},"BA50":{"r":"HL7250","t":"B735","f":"00","desc":"Boeing 737 58E"},"BA60":{"r":"PK-LIH","t":"B734","f":"00","desc":"Boeing 737 4Y0"},"BA95":{"r":"HL7295","t":"A306","f":"00","desc":""},"BA97":{"r":"HL7297","t":"A306","f":"00","desc":""},"BA99":{"r":"HL7299","t":"A306","f":"00","desc":""},"BB01":{"r":"HL7301","t":"F900","f":"00","desc":""},"BC00":{"r":"HL7400","t":"B744","f":"00","desc":"Boeing 747 4B5F"},"BC02":{"r":"HL7402","t":"B744","f":"00","desc":"Boeing 747 4B5"},"BC03":{"r":"HL7403","t":"B744","f":"00","desc":"Boeing 747 4B5F"},"BC04":{"r":"HL7404","t":"B744","f":"00","desc":"Boeing 747 4B5"},"BC05":{"r":"HL7405","t":"B742","f":"00","desc":""},"BC07":{"r":"HL7407","t":"B744","f":"00","desc":""},"BC08":{"r":"HL7408","t":"B742","f":"00","desc":""},"BC12":{"r":"HL7412","t":"B744","f":"00","desc":""},"BC13":{"r":"HL7413","t":"B744","f":"00","desc":"Boeing 747 48E BDSF"},"BC14":{"r":"HL7414","t":"B744","f":"00","desc":"Boeing 747 48E BDSF"},"BC15":{"r":"HL7415","t":"B744","f":"00","desc":"Boeing 747 48E BDSF"},"BC17":{"r":"HL7417","t":"B744","f":"00","desc":"Boeing 747 48E BDSF"},"BC18":{"r":"HL7418","t":"B744","f":"00","desc":"Boeing 747 48E"},"BC19":{"r":"HL7419","t":"B744","f":"00","desc":"Boeing 747 48EFSCD"},"BC20":{"r":"HL7420","t":"B744","f":"00","desc":"Boeing 747 48EFSCD"},"BC21":{"r":"HL7421","t":"B744","f":"00","desc":"Boeing 747 48EFSCD"},"BC22":{"r":"HL7422","t":"B744","f":"00","desc":""},"BC23":{"r":"HL7423","t":"B744","f":"00","desc":"Boeing 747 48EFSCD"},"BC26":{"r":"HL7426","t":"B744","f":"00","desc":""},"BC28":{"r":"HL7428","t":"B744","f":"00","desc":"Boeing 747 48E"},"BC34":{"r":"HL7434","t":"B744","f":"00","desc":"Boeing 747 4B5F"},"BC36":{"r":"HL7436","t":"B744","f":"00","desc":"Boeing 747 48EFSCD"},"BC37":{"r":"HL7437","t":"B744","f":"00","desc":"Boeing 747 4B5F"},"BC38":{"r":"HL7438","t":"B744","f":"00","desc":"Boeing 747 4B5ERF"},"BC39":{"r":"HL7439","t":"B744","f":"00","desc":"Boeing 747 4B5ERF"},"BC41":{"r":"HL7441","t":"B744","f":"00","desc":""},"BC48":{"r":"HL7448","t":"B744","f":"00","desc":"Boeing 747 4B5F"},"BC49":{"r":"HL7449","t":"B744","f":"00","desc":"Boeing 747 4B5F"},"BC60":{"r":"HL7460","t":"B744","f":"00","desc":"Boeing 747 4B5"},"BC61":{"r":"HL7461","t":"B744","f":"00","desc":"Boeing 747 4B5"},"BC62":{"r":"HL7462","t":"B744","f":"00","desc":"Boeing 747 4B5F"},"BC65":{"r":"10001","t":"B744","f":"01","desc":"747-4B5"},"BC66":{"r":"HL7466","t":"B744","f":"00","desc":"Boeing 747 4B5F"},"BC67":{"r":"HL7467","t":"B744","f":"00","desc":"Boeing 747 4B5F"},"BC72":{"r":"HL7472","t":"B744","f":"00","desc":"Boeing 747 4B5"},"BC73":{"r":"HL7473","t":"B744","f":"00","desc":"Boeing 747 4B5"},"BC80":{"r":"HL7480","t":"B744","f":"00","desc":""},"BC82":{"r":"HL7482","t":"B744","f":"00","desc":""},"BC83":{"r":"HL7483","t":"B744","f":"00","desc":""},"BC84":{"r":"HL7484","t":"B744","f":"00","desc":""},"BC85":{"r":"HL7485","t":"B744","f":"00","desc":""},"BC86":{"r":"HL7486","t":"B744","f":"00","desc":""},"BC87":{"r":"HL7487","t":"B744","f":"00","desc":""},"BC88":{"r":"HL7488","t":"B744","f":"00","desc":""},"BC89":{"r":"HL7489","t":"B744","f":"00","desc":""},"BC90":{"r":"HL7490","t":"B744","f":"00","desc":"Boeing 747 4B5"},"BC91":{"r":"HL7491","t":"B744","f":"00","desc":""},"BC92":{"r":"HL7492","t":"B744","f":"00","desc":"Boeing 747 4B5"},"BC93":{"r":"HL7493","t":"B744","f":"00","desc":"Boeing 747 4B5"},"BC94":{"r":"HL7494","t":"B744","f":"00","desc":"Boeing 747 4B5"},"BC95":{"r":"HL7495","t":"B744","f":"00","desc":"Boeing 747 4B5"},"BC98":{"r":"HL7498","t":"B744","f":"00","desc":"Boeing 747 4B5"},"BC99":{"r":"HL7499","t":"B744","f":"00","desc":"Boeing 747 4B5ERF"},"BD00":{"r":"HL7500","t":"B772","f":"00","desc":""},"BD06":{"r":"HL7506","t":"B763","f":"00","desc":"Boeing 767 38E"},"BD07":{"r":"HL7507","t":"B763","f":"00","desc":"Boeing 767 38EERF"},"BD08":{"r":"HL7508","t":"B734","f":"00","desc":"Boeing 737 48E"},"BD10":{"r":"HL7510","t":"B734","f":"00","desc":"Boeing 737 48E"},"BD13":{"r":"HL7513","t":"B734","f":"00","desc":"Boeing 737 48E"},"BD14":{"r":"HL7514","t":"B763","f":"00","desc":"Boeing 767 38E"},"BD15":{"r":"HL7515","t":"B763","f":"00","desc":"Boeing 767 38E"},"BD16":{"r":"HL7516","t":"B763","f":"00","desc":"Boeing 767 38E"},"BD17":{"r":"HL7517","t":"B734","f":"00","desc":"Boeing 737 48E"},"BD24":{"r":"HL7524","t":"A333","f":"00","desc":"Airbus A330 322"},"BD25":{"r":"HL7525","t":"A333","f":"00","desc":"Airbus A330 322"},"BD26":{"r":"HL7526","t":"B772","f":"00","desc":"Boeing 777 2B5ER"},"BD28":{"r":"HL7528","t":"B763","f":"00","desc":"Boeing 767 38E"},"BD30":{"r":"HL7530","t":"B772","f":"00","desc":"Boeing 777 2B5ER"},"BD31":{"r":"HL7531","t":"B772","f":"00","desc":"Boeing 777 2B5ER"},"BD32":{"r":"HL7532","t":"B773","f":"00","desc":"Boeing 777 3B5"},"BD33":{"r":"HL7533","t":"B773","f":"00","desc":"Boeing 777 3B5"},"BD34":{"r":"HL7534","t":"B773","f":"00","desc":"Boeing 777 3B5"},"BD38":{"r":"HL7538","t":"A332","f":"00","desc":"Airbus A330 223"},"BD39":{"r":"HL7539","t":"A332","f":"00","desc":"Airbus A330 223"},"BD40":{"r":"HL7540","t":"A333","f":"00","desc":"Airbus A330 322"},"BD50":{"r":"HL7550","t":"A333","f":"00","desc":"Airbus A330 322"},"BD51":{"r":"HL7551","t":"A333","f":"00","desc":"Airbus A330 322"},"BD52":{"r":"HL7552","t":"A332","f":"00","desc":"Airbus A330 223"},"BD53":{"r":"HL7553","t":"A333","f":"00","desc":"Airbus A330 323X"},"BD54":{"r":"HL7554","t":"A333","f":"00","desc":"Airbus A330 323X"},"BD55":{"r":"HL7555","t":"B738","f":"00","desc":"Boeing 737NG 86N"},"BD56":{"r":"HL7556","t":"B738","f":"00","desc":"Boeing 737NG 86N"},"BD57":{"r":"HL7557","t":"B738","f":"00","desc":"Boeing 737NG 86N"},"BD58":{"r":"HL7558","t":"B738","f":"00","desc":"Boeing 737NG 86N"},"BD59":{"r":"HL7559","t":"B738","f":"00","desc":"Boeing 737NG 86N"},"BD60":{"r":"HL7560","t":"B738","f":"00","desc":"Boeing 737NG 8B5\/W"},"BD61":{"r":"HL7561","t":"B738","f":"00","desc":"Boeing 737NG 8B5\/W"},"BD62":{"r":"HL7562","t":"B738","f":"00","desc":"Boeing 737NG 8B5\/W"},"BD63":{"r":"HL7563","t":"B738","f":"00","desc":"Boeing 737NG 86N\/W"},"BD64":{"r":"HL7564","t":"B738","f":"00","desc":"Boeing 737NG 86N"},"BD65":{"r":"HL7565","t":"B738","f":"00","desc":"Boeing 737NG 8B5\/W"},"BD66":{"r":"HL7566","t":"B738","f":"00","desc":"Boeing 737NG 8B5\/W"},"BD67":{"r":"HL7567","t":"B738","f":"00","desc":"Boeing 737NG 86N"},"BD68":{"r":"HL7568","t":"B738","f":"00","desc":"Boeing 737NG 8B5\/W"},"BD69":{"r":"HL7569","t":"B739","f":"00","desc":"Boeing 737NG 9B5"},"BD73":{"r":"HL7573","t":"B773","f":"00","desc":"Boeing 777 3B5"},"BD74":{"r":"HL7574","t":"B772","f":"00","desc":"Boeing 777 2B5ER"},"BD75":{"r":"HL7575","t":"B772","f":"00","desc":"Boeing 777 2B5ER"},"BD84":{"r":"HL7584","t":"A333","f":"00","desc":"Airbus A330 323X"},"BD85":{"r":"HL7585","t":"A333","f":"00","desc":"Airbus A330 323X"},"BD86":{"r":"HL7586","t":"A333","f":"00","desc":"Airbus A330 323X"},"BD87":{"r":"HL7587","t":"A333","f":"00","desc":"Airbus A330 323X"},"BD94":{"r":"HL7594","t":"A321","f":"00","desc":"Airbus A321 131"},"BD96":{"r":"HL7596","t":"B772","f":"00","desc":"Boeing 777 28EER"},"BD97":{"r":"HL7597","t":"B772","f":"00","desc":"Boeing 777 28EER"},"BD98":{"r":"HL7598","t":"B772","f":"00","desc":"Boeing 777 2B5ER"},"BD99":{"r":"HL7599","t":"B739","f":"00","desc":"Boeing 737NG 9B5"},"BE00":{"r":"HL7600","t":"B744","f":"00","desc":"Boeing 747 4B5ERF"},"BE01":{"r":"HL7601","t":"B744","f":"00","desc":"Boeing 747 4B5ERF"},"BE02":{"r":"HL7602","t":"B744","f":"00","desc":"Boeing 747 4B5ERF"},"BE03":{"r":"HL7603","t":"B744","f":"00","desc":"Boeing 747 4B5ERF"},"BE04":{"r":"HL7604","t":"B744","f":"00","desc":""},"BE05":{"r":"HL7605","t":"B744","f":"00","desc":"Boeing 747 4B5ERF"},"BE06":{"r":"HL7606","t":"B744","f":"00","desc":""},"BE07":{"r":"HL7607","t":"B744","f":"00","desc":""},"BE08":{"r":"HL7608","t":"B744","f":"00","desc":""},"BE09":{"r":"HL7609","t":"B748","f":"00","desc":"Boeing 747 8HTF"},"BE10":{"r":"HL7610","t":"B748","f":"00","desc":"Boeing 747 8HTF"},"BE11":{"r":"HL7611","t":"A388","f":"00","desc":"Airbus A380 861"},"BE12":{"r":"HL7612","t":"A388","f":"00","desc":"Airbus A380 861"},"BE13":{"r":"HL7613","t":"A388","f":"00","desc":"Airbus A380 861"},"BE14":{"r":"HL7614","t":"A388","f":"00","desc":"Airbus A380 861"},"BE15":{"r":"HL7615","t":"A388","f":"00","desc":"Airbus A380 861"},"BE16":{"r":"HL7616","t":"B744","f":"00","desc":"Boeing 747 446FSCD"},"BE17":{"r":"HL7617","t":"B748","f":"00","desc":"Boeing 747 8B5F"},"BE18":{"r":"HL7618","t":"B744","f":"00","desc":"Boeing 747 446FSCD"},"BE19":{"r":"HL7619","t":"A388","f":"00","desc":"Airbus A380 861"},"BE20":{"r":"HL7620","t":"B744","f":"00","desc":"Boeing 747 419 BDSF"},"BE21":{"r":"HL7621","t":"A388","f":"00","desc":"Airbus A380 861"},"BE22":{"r":"HL7622","t":"A388","f":"00","desc":"Airbus A380 861"},"BE23":{"r":"HL7623","t":"B748","f":"00","desc":"Boeing 747 8B5F"},"BE24":{"r":"HL7624","t":"B748","f":"00","desc":"Boeing 747 8B5F"},"BE25":{"r":"HL7625","t":"A388","f":"00","desc":"Airbus A380 841"},"BE26":{"r":"HL7626","t":"A388","f":"00","desc":"Airbus A380 841"},"BE27":{"r":"HL7627","t":"A388","f":"00","desc":"Airbus A380 861"},"BE28":{"r":"HL7628","t":"A388","f":"00","desc":"Airbus A380 861"},"BE29":{"r":"HL7629","t":"B748","f":"00","desc":"Boeing 747 8B5F"},"BE30":{"r":"HL7630","t":"B748","f":"00","desc":"Boeing 747 8B5"},"BE31":{"r":"HL7631","t":"B748","f":"00","desc":"Boeing 747 8B5"},"BE32":{"r":"HL7632","t":"B748","f":"00","desc":"Boeing 747 8B5"},"BE33":{"r":"HL7633","t":"B748","f":"00","desc":"Boeing 747 8B5"},"BE34":{"r":"HL7634","t":"A388","f":"00","desc":"Airbus A380 841"},"BE35":{"r":"HL7635","t":"A388","f":"00","desc":"Airbus A380 841"},"BE36":{"r":"HL7636","t":"B748","f":"00","desc":"Boeing 747 8B5"},"BE37":{"r":"HL7637","t":"B748","f":"00","desc":"Boeing 747 8B5"},"BE38":{"r":"HL7638","t":"B748","f":"00","desc":"Boeing 747 8B5"},"BE39":{"r":"HL7639","t":"B748","f":"00","desc":"Boeing 747 8B5F"},"BE40":{"r":"HL7640","t":"A388","f":"00","desc":"Airbus A380 841"},"BE41":{"r":"HL7641","t":"A388","f":"00","desc":"Airbus A380 841"},"BE42":{"r":"HL7642","t":"B748","f":"00","desc":"Boeing 747 8I"},"BF00":{"r":"HL7700","t":"B772","f":"00","desc":"Boeing 777 28EER"},"BF01":{"r":"HL7701","t":"A333","f":"00","desc":""},"BF02":{"r":"HL7702","t":"A333","f":"00","desc":"Airbus A330 323X"},"BF03":{"r":"HL7703","t":"A321","f":"00","desc":"Airbus A321 131"},"BF04":{"r":"HL7704","t":"B739","f":"00","desc":"Boeing 737NG 9B5"},"BF05":{"r":"HL7705","t":"B739","f":"00","desc":"Boeing 737NG 9B5"},"BF06":{"r":"HL7706","t":"B739","f":"00","desc":"Boeing 737NG 9B5"},"BF07":{"r":"HL7707","t":"B739","f":"00","desc":"Boeing 737NG 9B5"},"BF08":{"r":"HL7708","t":"B739","f":"00","desc":"Boeing 737NG 9B5"},"BF09":{"r":"HL7709","t":"A333","f":"00","desc":"Airbus A330 323X"},"BF10":{"r":"HL7710","t":"A333","f":"00","desc":"Airbus A330 323X"},"BF11":{"r":"HL7711","t":"A321","f":"00","desc":"Airbus A321 231"},"BF12":{"r":"HL7712","t":"A321","f":"00","desc":"Airbus A321 231"},"BF13":{"r":"HL7713","t":"A321","f":"00","desc":"Airbus A321 231"},"BF14":{"r":"HL7714","t":"B772","f":"00","desc":"Boeing 777 2B5ER"},"BF15":{"r":"HL7715","t":"B772","f":"00","desc":"Boeing 777 2B5ER"},"BF16":{"r":"HL7716","t":"B739","f":"00","desc":"Boeing 737NG 9B5"},"BF17":{"r":"HL7717","t":"B739","f":"00","desc":"Boeing 737NG 9B5"},"BF18":{"r":"HL7718","t":"B739","f":"00","desc":"Boeing 737NG 9B5"},"BF19":{"r":"HL7719","t":"B739","f":"00","desc":"Boeing 737NG 9B5"},"BF20":{"r":"HL7720","t":"A333","f":"00","desc":"Airbus A330 323X"},"BF21":{"r":"HL7721","t":"B772","f":"00","desc":"Boeing 777 2B5ER"},"BF22":{"r":"HL7722","t":"A321","f":"00","desc":"Airbus A321 231"},"BF23":{"r":"HL7723","t":"A321","f":"00","desc":"Airbus A321 231"},"BF24":{"r":"HL7724","t":"B739","f":"00","desc":"Boeing 737NG 9B5"},"BF25":{"r":"HL7725","t":"B739","f":"00","desc":"Boeing 737NG 9B5"},"BF26":{"r":"HL7726","t":"B739","f":"00","desc":"Boeing 737NG 9B5"},"BF27":{"r":"HL7727","t":"B739","f":"00","desc":"Boeing 737NG 9B5"},"BF28":{"r":"HL7728","t":"B739","f":"00","desc":"Boeing 737NG 9B5"},"BF29":{"r":"HL7729","t":"A321","f":"00","desc":"Airbus A321 231"},"BF30":{"r":"HL7730","t":"A321","f":"00","desc":"Airbus A321 231"},"BF31":{"r":"HL7731","t":"A321","f":"00","desc":"Airbus A321 231"},"BF32":{"r":"HL7732","t":"B772","f":"00","desc":"Boeing 777 28EER"},"BF33":{"r":"HL7733","t":"B772","f":"00","desc":"Boeing 777 2B5ER"},"BF34":{"r":"HL7734","t":"B772","f":"00","desc":"Boeing 777 2B5ER"},"BF35":{"r":"HL7735","t":"A321","f":"00","desc":"Airbus A321 231"},"BF36":{"r":"HL7736","t":"A333","f":"00","desc":"Airbus A330 323E"},"BF37":{"r":"HL7737","t":"A320","f":"00","desc":"Airbus A320 232"},"BF38":{"r":"HL7738","t":"A320","f":"00","desc":"Airbus A320 232"},"BF39":{"r":"HL7739","t":"B772","f":"00","desc":"Boeing 777 28EER"},"BF40":{"r":"HL7740","t":"A333","f":"00","desc":"Airbus A330 323E"},"BF41":{"r":"HL7741","t":"A333","f":"00","desc":"Airbus A330 323E"},"BF42":{"r":"HL7742","t":"B772","f":"00","desc":""},"BF43":{"r":"HL7743","t":"B772","f":"00","desc":"Boeing 777 2B5ER"},"BF44":{"r":"HL7744","t":"A320","f":"00","desc":"Airbus A320 232"},"BF45":{"r":"HL7745","t":"A320","f":"00","desc":"Airbus A320 232"},"BF46":{"r":"HL7746","t":"A333","f":"00","desc":"Airbus A330 323E"},"BF47":{"r":"HL7747","t":"A333","f":"00","desc":"Airbus A330 323E"},"BF48":{"r":"HL7748","t":"GLEX","f":"00","desc":""},"BF49":{"r":"HL7749","t":"GLEX","f":"00","desc":""},"BF50":{"r":"HL7750","t":"B772","f":"00","desc":"Boeing 777 2B5ER"},"BF51":{"r":"HL7751","t":"B772","f":"00","desc":"Boeing 777 2B5ER"},"BF52":{"r":"HL7752","t":"B772","f":"00","desc":"Boeing 777 2B5ER"},"BF53":{"r":"HL7753","t":"A320","f":"00","desc":"Airbus A320 232"},"BF54":{"r":"HL7754","t":"A333","f":"00","desc":"Airbus A330 323E"},"BF55":{"r":"HL7755","t":"B772","f":"00","desc":"Boeing 777 28EER"},"BF56":{"r":"HL7756","t":"B772","f":"00","desc":"Boeing 777 28EER"},"BF57":{"r":"HL7757","t":"B738","f":"00","desc":"Boeing 737NG 8GQ\/W"},"BF58":{"r":"HL7758","t":"B738","f":"00","desc":"Boeing 737NG 8GQ\/W"},"BF59":{"r":"HL7759","t":"B737","f":"00","desc":"Boeing 737NG 7EG\/W BBJ"},"BF61":{"r":"HL7761","t":"A321","f":"00","desc":"Airbus A321 232"},"BF62":{"r":"HL7762","t":"A320","f":"00","desc":""},"BF63":{"r":"HL7763","t":"A321","f":"00","desc":"Airbus A321 231"},"BF64":{"r":"HL7764","t":"B772","f":"00","desc":"Boeing 777 2B5ER"},"BF65":{"r":"HL7765","t":"B772","f":"00","desc":"Boeing 777 2B5ER"},"BF66":{"r":"HL7766","t":"B772","f":"00","desc":"Boeing 777 2B5ER"},"BF67":{"r":"HL7767","t":"A321","f":"00","desc":"Airbus A321 232"},"BF69":{"r":"HL7769","t":"A320","f":"00","desc":"Airbus A320 232"},"BF70":{"r":"HL7770","t":"B737","f":"00","desc":""},"BF72":{"r":"HL7772","t":"A320","f":"00","desc":"Airbus A320 232"},"BF73":{"r":"HL7773","t":"A320","f":"00","desc":"Airbus A320 232"},"BF75":{"r":"HL7775","t":"B772","f":"00","desc":"Boeing 777 28EER"},"BF76":{"r":"HL7776","t":"A320","f":"00","desc":"Airbus A320 232"},"BF77":{"r":"HL7777","t":"F100","f":"00","desc":""},"BF79":{"r":"HL7779","t":"B738","f":"00","desc":"Boeing 737NG 85F"},"BF80":{"r":"HL7780","t":"B738","f":"00","desc":"Boeing 737NG 85F"},"BF81":{"r":"HL7781","t":"B736","f":"00","desc":""},"BF82":{"r":"HL7782","t":"B773","f":"00","desc":"Boeing 777 3B5ER"},"BF83":{"r":"HL7783","t":"B773","f":"00","desc":"Boeing 777 3B5ER"},"BF84":{"r":"HL7784","t":"B773","f":"00","desc":"Boeing 777 3B5ER"},"BF85":{"r":"HL7785","t":"B738","f":"00","desc":"Boeing 737NG 8Q8"},"BF86":{"r":"HL7786","t":"B738","f":"00","desc":"Boeing 737NG 8Q8"},"BF87":{"r":"HL7787","t":"B737","f":"00","desc":"Boeing 737NG 75G BBJ"},"BF88":{"r":"HL7788","t":"A320","f":"00","desc":"Airbus A320 232"},"BF89":{"r":"HL7789","t":"A321","f":"00","desc":"Airbus A321 231"},"BF90":{"r":"HL7790","t":"A321","f":"00","desc":"Airbus A321 231"},"BF91":{"r":"HL7791","t":"B772","f":"00","desc":"Boeing 777 28EER"},"BF92":{"r":"HL7792","t":"A333","f":"00","desc":"Airbus A330 323E"},"BF93":{"r":"HL7793","t":"A333","f":"00","desc":"Airbus A330 323E"},"BF94":{"r":"HL7794","t":"A333","f":"00","desc":"Airbus A330 323E"},"BF95":{"r":"HL7795","t":"A333","f":"00","desc":"Airbus A330 323E"},"BF96":{"r":"HL7796","t":"B738","f":"00","desc":""},"BF97":{"r":"HL7797","t":"B737","f":"00","desc":""},"BF98":{"r":"HL7798","t":"B738","f":"00","desc":"Boeing 737NG 809\/W"},"BF99":{"r":"HL7799","t":"GLF5","f":"00","desc":""},"C000":{"r":"HL8000","t":"B738","f":"00","desc":"737-86N (W)"},"C001":{"r":"HL8001","t":"A333","f":"00","desc":"Airbus A330 323E"},"C002":{"r":"HL8002","t":"A333","f":"00","desc":"Airbus A330 323E"},"C003":{"r":"HL8003","t":"A333","f":"00","desc":"Airbus A330 323E"},"C004":{"r":"HL8004","t":"A321","f":"00","desc":"Airbus A321 232"},"C005":{"r":"HL8005","t":"B77L","f":"00","desc":"Boeing 777 FB5"},"C006":{"r":"HL8006","t":"B773","f":"00","desc":"Boeing 777 3B5ER"},"C007":{"r":"HL8007","t":"B773","f":"00","desc":"Boeing 777 3B5ER"},"C008":{"r":"HL8008","t":"B773","f":"00","desc":"Boeing 777 3B5ER"},"C009":{"r":"HL8009","t":"B773","f":"00","desc":"Boeing 777 3B5ER"},"C010":{"r":"HL8010","t":"B773","f":"00","desc":"Boeing 777 3B5ER"},"C011":{"r":"HL8011","t":"B773","f":"00","desc":"Boeing 777 3B5ER"},"C012":{"r":"HL8012","t":"B738","f":"00","desc":"Boeing 737NG 8SH\/W"},"C013":{"r":"HL8013","t":"B738","f":"00","desc":"Boeing 737NG 8SH\/W"},"C014":{"r":"HL8014","t":"B738","f":"00","desc":"Boeing 737NG 8SH\/W"},"C015":{"r":"HL8015","t":"B738","f":"00","desc":"Boeing 737NG 8SH\/W"},"C016":{"r":"HL8016","t":"B738","f":"00","desc":"Boeing 737NG 8SH\/W"},"C017":{"r":"HL8017","t":"B738","f":"00","desc":"Boeing 737NG 8SH\/W"},"C018":{"r":"HL8018","t":"A321","f":"00","desc":"Airbus A321 231"},"C019":{"r":"HL8019","t":"B738","f":"00","desc":"Boeing 737NG 86N\/W"},"C020":{"r":"HL8020","t":"B738","f":"00","desc":"Boeing 737NG 86N"},"C021":{"r":"HL8021","t":"B738","f":"00","desc":"Boeing 737NG 8GJ\/W"},"C022":{"r":"HL8022","t":"B737","f":"00","desc":"Boeing 737NG 73V"},"C023":{"r":"HL8023","t":"B738","f":"00","desc":"Boeing 737NG 86N"},"C024":{"r":"HL8024","t":"B738","f":"00","desc":"Boeing 737NG 8HX\/W"},"C025":{"r":"HL8025","t":"A333","f":"00","desc":"Airbus A330 323E"},"C026":{"r":"HL8026","t":"A333","f":"00","desc":"Airbus A330 323E"},"C027":{"r":"HL8027","t":"A333","f":"00","desc":"Airbus A330 323E"},"C028":{"r":"HL8028","t":"B738","f":"00","desc":"Boeing 737NG 8BK"},"C029":{"r":"HL8029","t":"B738","f":"00","desc":"Boeing 737NG 86N"},"C030":{"r":"HL8030","t":"B738","f":"00","desc":"Boeing 737NG 8Q8\/W"},"C031":{"r":"HL8031","t":"B738","f":"00","desc":"Boeing 737NG 8GJ\/W"},"C032":{"r":"HL8032","t":"B738","f":"00","desc":"Boeing 737NG 8GJ\/W"},"C033":{"r":"HL8033","t":"B738","f":"00","desc":"Boeing 737NG 8AL\/W"},"C034":{"r":"HL8034","t":"B738","f":"00","desc":"Boeing 737NG 8HX\/W"},"C035":{"r":"HL8035","t":"B738","f":"00","desc":"Boeing 737NG 8BK\/W"},"C036":{"r":"HL8036","t":"B738","f":"00","desc":"Boeing 737NG 86N"},"C038":{"r":"HL8038","t":"A321","f":"00","desc":"Airbus A321 231SL"},"C039":{"r":"HL8039","t":"A321","f":"00","desc":"Airbus A321 231SL"},"C040":{"r":"HL8040","t":"CRJ2","f":"00","desc":"Bombardier CRJ 200ER"},"C041":{"r":"HL8041","t":"B773","f":"00","desc":"Boeing 777 3B5ER"},"C042":{"r":"HL8042","t":"B773","f":"00","desc":"Boeing 777 3B5ER"},"C043":{"r":"HL8043","t":"B77L","f":"00","desc":"Boeing 777 FB5"},"C044":{"r":"HL8044","t":"B77L","f":"00","desc":"777-FB5"},"C045":{"r":"HL8045","t":"B77L","f":"00","desc":"Boeing 777 FB5"},"C046":{"r":"HL8046","t":"B77L","f":"00","desc":"Boeing 777 FB5"},"C047":{"r":"HL8047","t":"B738","f":"00","desc":"Boeing 737NG 8BK\/W"},"C048":{"r":"HL8048","t":"B738","f":"00","desc":"Boeing 737NG 808\/W"},"C049":{"r":"HL8049","t":"B738","f":"00","desc":"Boeing 737NG 8AS\/W"},"C050":{"r":"HL8050","t":"B738","f":"00","desc":"Boeing 737NG 8AS\/W"},"C051":{"r":"HL8051","t":"B738","f":"00","desc":"Boeing 737NG 8AS\/W"},"C052":{"r":"HL8052","t":"B738","f":"00","desc":"Boeing 737NG 86J\/W"},"C053":{"r":"HL8053","t":"B738","f":"00","desc":"Boeing 737NG 86J\/W"},"C055":{"r":"HL8055","t":"A320","f":"00","desc":"Airbus A320 232"},"C056":{"r":"HL8056","t":"B738","f":"00","desc":"Boeing 737NG 8AS\/W"},"C057":{"r":"HL8057","t":"B738","f":"00","desc":"Boeing 737NG 86J\/W"},"C058":{"r":"HL8058","t":"B738","f":"00","desc":"Boeing 737NG 86J\/W"},"C059":{"r":"HL8059","t":"A321","f":"00","desc":"Airbus A321 231SL"},"C060":{"r":"HL8060","t":"A321","f":"00","desc":"Airbus A321 231SL"},"C061":{"r":"HL8061","t":"B738","f":"00","desc":"Boeing 737NG 8AS\/W"},"C062":{"r":"HL8062","t":"B738","f":"00","desc":"Boeing 737NG 8AS\/W"},"C063":{"r":"HL8063","t":"B738","f":"00","desc":"Boeing 737NG 8AS\/W"},"C064":{"r":"HL8064","t":"B738","f":"00","desc":"Boeing 737NG 8AS\/W"},"C065":{"r":"HL8065","t":"A320","f":"00","desc":"Airbus A320 232"},"C066":{"r":"HL8066","t":"A320","f":"00","desc":"Airbus A320 232"},"C067":{"r":"HL8067","t":"B738","f":"00","desc":"Boeing 737NG 8Q8"},"C069":{"r":"HL8069","t":"B738","f":"00","desc":"Boeing 737NG 8AS\/W"},"C070":{"r":"HL8070","t":"B738","f":"00","desc":"Boeing 737NG 8AS\/W"},"C071":{"r":"HL8071","t":"A321","f":"00","desc":"Airbus A321 231SL"},"C073":{"r":"HL8073","t":"A321","f":"00","desc":"Airbus A321 231"},"C074":{"r":"HL8074","t":"A321","f":"00","desc":"Airbus A321 231SL"},"C075":{"r":"HL8075","t":"B77L","f":"00","desc":"Boeing 777 FEZ"},"C076":{"r":"HL8076","t":"B77L","f":"00","desc":"777-FB5"},"C080":{"r":"HL8080","t":"A319","f":"00","desc":"Airbus ACJ319 115XSL"},"C081":{"r":"HL8081","t":"B789","f":"00","desc":"Boeing 787 9"},"C086":{"r":"HL8086","t":"B738","f":"00","desc":"Boeing 737NG 8Q8"},"C087":{"r":"HL8087","t":"B738","f":"00","desc":"Boeing 737NG 8AS\/W"},"C088":{"r":"HL8088","t":"B738","f":"00","desc":"Boeing 737NG 8AS\/W"},"C200":{"r":"HL8200","t":"GLF5","f":"00","desc":"Gulfstream Aerospace G550"},"C202":{"r":"HL8202","t":"C525","f":"00","desc":"Cessna Citation CJ1+"},"C204":{"r":"HL8204","t":"B737","f":"00","desc":""},"C205":{"r":"HL8205","t":"B737","f":"00","desc":"Boeing 737NG 73V"},"C206":{"r":"HL8206","t":"B738","f":"00","desc":"Boeing 737NG 86J\/W"},"C207":{"r":"HL8207","t":"B737","f":"00","desc":"Boeing 737NG 73V"},"C208":{"r":"HL8208","t":"B773","f":"00","desc":"Boeing 777 3B5ER"},"C209":{"r":"HL8209","t":"B773","f":"00","desc":"Boeing 777 3B5ER"},"C210":{"r":"HL8210","t":"B773","f":"00","desc":"Boeing 777 3B5ER"},"C211":{"r":"HL8211","t":"A332","f":"00","desc":"Airbus A330 223"},"C212":{"r":"HL8212","t":"A332","f":"00","desc":"Airbus A330 223"},"C213":{"r":"HL8213","t":"A321","f":"00","desc":"Airbus A321 231"},"C214":{"r":"HL8214","t":"B738","f":"00","desc":"Boeing 737NG 86N\/W"},"C215":{"r":"HL8215","t":"B737","f":"00","desc":""},"C216":{"r":"HL8216","t":"B773","f":"00","desc":"Boeing 777 3B5ER"},"C217":{"r":"HL8217","t":"B773","f":"00","desc":"Boeing 777 3B5ER"},"C218":{"r":"HL8218","t":"B773","f":"00","desc":"Boeing 777 3B5ER"},"C221":{"r":"HL8221","t":"B739","f":"00","desc":"Boeing 737NG 9B5ER\/W"},"C222":{"r":"HL8222","t":"B737","f":"00","desc":"Boeing 737NG 7B5 BBJ"},"C223":{"r":"HL8223","t":"B739","f":"00","desc":"Boeing 737NG 9B5ER\/W"},"C224":{"r":"HL8224","t":"B738","f":"00","desc":"Boeing 737NG 8Q8\/W"},"C225":{"r":"HL8225","t":"B738","f":"00","desc":"Boeing 737NG 8Q8\/W"},"C226":{"r":"HL8226","t":"B77L","f":"00","desc":"Boeing 777 FB5"},"C227":{"r":"HL8227","t":"A332","f":"00","desc":"Airbus A330 223"},"C228":{"r":"HL8228","t":"A332","f":"00","desc":"Airbus A330 223"},"C230":{"r":"HL8230","t":"GLEX","f":"00","desc":"Bombardier Global Express XRS"},"C232":{"r":"HL8232","t":"B738","f":"00","desc":"Boeing 737NG 8K5\/W"},"C234":{"r":"HL8234","t":"B738","f":"00","desc":"Boeing 737NG 86Q\/W"},"C235":{"r":"HL8235","t":"B738","f":"00","desc":"Boeing 737NG 8KG\/W"},"C236":{"r":"HL8236","t":"A321","f":"00","desc":"Airbus A321 231"},"C237":{"r":"HL8237","t":"B738","f":"00","desc":"Boeing 737NG 8Q8\/W"},"C238":{"r":"HL8238","t":"GLEX","f":"00","desc":"Bombardier Global Express XRS"},"C239":{"r":"HL8239","t":"B738","f":"00","desc":"Boeing 737NG 82R"},"C240":{"r":"HL8240","t":"B738","f":"00","desc":"Boeing 737NG 8BK\/W"},"C241":{"r":"HL8241","t":"B738","f":"00","desc":"Boeing 737NG 8BK\/W"},"C242":{"r":"HL8242","t":"B738","f":"00","desc":"Boeing 737NG 8Q8\/W"},"C243":{"r":"HL8243","t":"B738","f":"00","desc":"Boeing 737NG 8Q8\/W"},"C244":{"r":"HL8244","t":"B738","f":"00","desc":"Boeing 737NG 8Q8\/W"},"C245":{"r":"HL8245","t":"B738","f":"00","desc":"Boeing 737NG 8Q8\/W"},"C246":{"r":"HL8246","t":"B738","f":"00","desc":"Boeing 737NG 8LH\/W"},"C247":{"r":"HL8247","t":"B738","f":"00","desc":"Boeing 737NG 8SH\/W"},"C248":{"r":"HL8248","t":"B739","f":"00","desc":"Boeing 737NG 9B5ER\/W"},"C249":{"r":"HL8249","t":"B739","f":"00","desc":"Boeing 737NG 9B5ER\/W"},"C250":{"r":"HL8250","t":"B773","f":"00","desc":"Boeing 777 3B5ER"},"C251":{"r":"HL8251","t":"B77L","f":"00","desc":"Boeing 777 FB5"},"C252":{"r":"HL8252","t":"B77L","f":"00","desc":"Boeing 777 FB5"},"C253":{"r":"HL8253","t":"B738","f":"00","desc":"Boeing 737NG 86J\/W"},"C254":{"r":"HL8254","t":"B772","f":"00","desc":"Boeing 777 28EER"},"C255":{"r":"HL8255","t":"A321","f":"00","desc":"Airbus A321 231"},"C256":{"r":"HL8256","t":"A321","f":"00","desc":"Airbus A321 231"},"C257":{"r":"HL8257","t":"A321","f":"00","desc":"Airbus A321 231"},"C258":{"r":"HL8258","t":"A333","f":"00","desc":"Airbus A330 323E"},"C259":{"r":"HL8259","t":"A333","f":"00","desc":"Airbus A330 323E"},"C260":{"r":"HL8260","t":"B738","f":"00","desc":"Boeing 737NG 8BK\/W"},"C261":{"r":"HL8261","t":"B738","f":"00","desc":"Boeing 737NG 8BK\/W"},"C262":{"r":"HL8262","t":"B738","f":"00","desc":""},"C263":{"r":"HL8263","t":"B738","f":"00","desc":"Boeing 737NG 82R"},"C264":{"r":"HL8264","t":"B738","f":"00","desc":"Boeing 737NG 86J\/W"},"C265":{"r":"HL8265","t":"A321","f":"00","desc":"Airbus A321 231"},"C266":{"r":"HL8266","t":"A321","f":"00","desc":"Airbus A321 231"},"C267":{"r":"HL8267","t":"A321","f":"00","desc":"Airbus A321 231"},"C268":{"r":"HL8268","t":"B738","f":"00","desc":"Boeing 737NG 83N\/W"},"C269":{"r":"HL8269","t":"B738","f":"00","desc":"Boeing 737NG 8Q8\/W"},"C270":{"r":"HL8270","t":"B737","f":"00","desc":"Boeing 737NG 7EG\/W BBJ"},"C271":{"r":"HL8271","t":"B734","f":"00","desc":"Boeing 737 4Y0SF"},"C272":{"r":"HL8272","t":"B739","f":"00","desc":"Boeing 737NG 9B5ER\/W"},"C273":{"r":"HL8273","t":"B739","f":"00","desc":"Boeing 737NG 9B5ER\/W"},"C274":{"r":"HL8274","t":"B773","f":"00","desc":"Boeing 777 3B5ER"},"C275":{"r":"HL8275","t":"B773","f":"00","desc":"Boeing 777 3B5ER"},"C276":{"r":"HL8276","t":"A332","f":"00","desc":"Airbus A330 223"},"C277":{"r":"HL8277","t":"A321","f":"00","desc":"Airbus A321 231"},"C278":{"r":"HL8278","t":"A321","f":"00","desc":"Airbus A321 231"},"C279":{"r":"HL8279","t":"A321","f":"00","desc":"Airbus A321 231"},"C280":{"r":"HL8280","t":"A321","f":"00","desc":"Airbus A321 231"},"C281":{"r":"HL8281","t":"A321","f":"00","desc":"Airbus A321 231"},"C282":{"r":"HL8282","t":"A333","f":"00","desc":"Airbus A330 323E"},"C283":{"r":"HL8283","t":"C525","f":"00","desc":"Cessna Citation CJ1+"},"C284":{"r":"HL8284","t":"B772","f":"00","desc":"Boeing 777 28EER"},"C285":{"r":"HL8285","t":"B77L","f":"00","desc":"Boeing 777 FB5"},"C286":{"r":"HL8286","t":"A333","f":"00","desc":"Airbus A330 323E"},"C287":{"r":"HL8287","t":"B738","f":"00","desc":"Boeing 737NG 8Q8\/W"},"C288":{"r":"HL8288","t":"GLF5","f":"00","desc":"Gulfstream Aerospace G550"},"C289":{"r":"HL8289","t":"B738","f":"00","desc":"Boeing 737NG 883"},"C290":{"r":"HL8290","t":"B737","f":"00","desc":"Boeing 737NG 7GE\/W BBJ"},"C292":{"r":"HL8292","t":"B738","f":"00","desc":"Boeing 737NG 883"},"C293":{"r":"HL8293","t":"A333","f":"00","desc":"Airbus A330 323E"},"C294":{"r":"HL8294","t":"B738","f":"00","desc":"Boeing 737NG 8Q8\/W"},"C295":{"r":"HL8295","t":"B738","f":"00","desc":"Boeing 737NG 8Q8\/W"},"C296":{"r":"HL8296","t":"B738","f":"00","desc":"Boeing 737NG 8Q8\/W"},"C297":{"r":"HL8297","t":"B738","f":"00","desc":"Boeing 737NG 83N\/W"},"C299":{"r":"HL8299","t":"GLF6","f":"00","desc":"Gulfstream Aerospace G650 ER"},"C962":{"r":"HL9162","t":"B06","f":"00","desc":"Bell 206L Long Ranger III"},"CA52":{"r":"HL9252","t":"S76","f":"00","desc":"Sikorsky S-76 C"},"CA66":{"r":"HL9266","t":"S76","f":"00","desc":"Sikorsky S-76 C"},"CA91":{"r":"HL9291","t":"S76","f":"00","desc":"Sikorsky S-76 C"},"CC75":{"r":"HL9475","t":"KA27","f":"00","desc":"Kamov Ka-32 A"},"CC81":{"r":"HL9481","t":"KA27","f":"00","desc":"Kamov Ka-32 A11BC"},"CC86":{"r":"HL9486","t":"KA27","f":"00","desc":"Kamov Ka-32 A"},"CC95":{"r":"HL9495","t":"EC35","f":"00","desc":"Eurocopter EC135 T2+"},"CC96":{"r":"HL9496","t":"EC35","f":"00","desc":"Eurocopter EC135 P2+"},"CC97":{"r":"HL9497","t":"EC35","f":"00","desc":"Eurocopter EC135 P2+"},"CE00":{"r":"HL9600","t":"S76","f":"00","desc":"Sikorsky S-76 D"},"CE04":{"r":"HL9604","t":"S76","f":"00","desc":"Sikorsky S-76 D"},"CE09":{"r":"HL9609","t":"A139","f":"00","desc":"AgustaWestland AW.139"},"CE10":{"r":"HL9610","t":"A139","f":"00","desc":"AgustaWestland AW.139"},"CE15":{"r":"HL9615","t":"A109","f":"00","desc":"AgustaWestland AW.109 SP Grand New"},"CE16":{"r":"HL9616","t":"EC35","f":"00","desc":"Eurocopter EC135 P2+"},"D121":{"r":"HL9121","t":"H500","f":"00","desc":"Hughes 369 MD"},"D177":{"r":"HL9177","t":"B06","f":"00","desc":"Bell 206L Long Ranger III"},"D250":{"r":"HL9250","t":"S76","f":"00","desc":"Sikorsky S-76 B"},"D400":{"r":"HL9400","t":"KA27","f":"00","desc":"Kamov Ka-32 T"},"D420":{"r":"HL9420","t":"KA27","f":"00","desc":"Kamov Ka-32 A"},"D426":{"r":"HL9426","t":"KA27","f":"00","desc":"Kamov Ka-32 T"},"D441":{"r":"HL9441","t":"ANST","f":"00","desc":"Kazan Helicopters Ansat"},"DF01":{"r":"B701","t":"CL60","f":"00","desc":"Bombardier Challenger 604"},"F60E":{"r":"30-088","t":"CN35","f":"00","desc":"CASA CN-235 100M"},"F801":{"r":"85101","t":"B733","f":"00","desc":"Boeing 737 3Z8"},"F901":{"r":"45-006","t":"C130","f":"00","desc":"Lockheed C-130H-30 Hercules"},"F903":{"r":"55-030","t":"C130","f":"00","desc":"Lockheed C-130H-30 Hercules"},"F904":{"r":"55-036","t":"C130","f":"00","desc":"Lockheed C-130H-30 Hercules"},"F905":{"r":"95-178","t":"C130","f":"00","desc":"Lockheed C-130H Hercules"},"F907":{"r":"95-180","t":"C130","f":"00","desc":"Lockheed C-130H Hercules"},"F909":{"r":"05-182","t":"C130","f":"00","desc":"Lockheed C-130H Hercules"},"F90A":{"r":"05-183","t":"C130","f":"10","desc":"Lockheed C-130H Hercules"},"F90B":{"r":"05-185","t":"C130","f":"00","desc":"Lockheed C-130H Hercules"},"F9C1":{"r":"35-730","t":"C30J","f":"00","desc":"Lockheed C-130J-30 Hercules"},"F9C3":{"r":"45-747","t":"C30J","f":"00","desc":"Lockheed C-130J-30 Hercules"},"F9C4":{"r":"45-750","t":"C30J","f":"00","desc":"Lockheed C-130J-30 Hercules"},"FA03":{"r":"20-046","t":"CN35","f":"00","desc":"IPTN CN-235 220M"},"FA06":{"r":"20-049","t":"CN35","f":"00","desc":"IPTN CN-235 220M"},"FA07":{"r":"02-050","t":"CN35","f":"00","desc":"IPTN CN-235 220VVIP"},"FA09":{"r":"30-078","t":"CN35","f":"00","desc":"CASA CN-235 100M"},"FA0A":{"r":"30-081","t":"CN35","f":"00","desc":"CASA CN-235 100M"},"FA0B":{"r":"30-082","t":"CN35","f":"00","desc":"CASA CN-235 100M"},"FA0D":{"r":"30-087","t":"CN35","f":"00","desc":"CASA CN-235 100M"},"FA10":{"r":"40-092","t":"CN35","f":"00","desc":"CASA CN-235 100M"},"FA11":{"r":"40-096","t":"CN35","f":"00","desc":"CASA CN-235 100M"},"FB02":{"r":"05050","t":"S92","f":"10","desc":"Sikorsky S-92 A"},"FC01":{"r":"64-700","t":"E737","f":"00","desc":"Boeing E-737 Wedgetail"},"FC02":{"r":"65-327","t":"E737","f":"00","desc":"Boeing E-737 Wedgetail"},"FC03":{"r":"65-328","t":"E737","f":"00","desc":"Boeing E-737 Wedgetail"},"FC04":{"r":"65-329","t":"E737","f":"00","desc":"Boeing E-737 Wedgetail"}}