{"004":{"r":"N898PJ","t":"M20P","f":"00","desc":""},"012":{"r":"N297GA","t":"G280","f":"00","desc":"Gulfstream Aerospace G280"},"013":{"r":"N297GB","t":"F900","f":"00","desc":"Dassault Falcon 900EX EASy"},"022":{"r":"N297GS","t":"A109","f":"00","desc":"Agusta A.109 A"},"023":{"r":"N297GT","t":"TB21","f":"00","desc":""},"038":{"r":"N297HP","t":"P32R","f":"00","desc":"Piper PA-32R 301 Saratoga SP"},"091":{"r":"N297MC","t":"CL30","f":"00","desc":"Bombardier Challenger 300"},"093":{"r":"N297ME","t":"C172","f":"00","desc":"Cessna 172S Skyhawk SP"},"095":{"r":"N297MG","t":"P28A","f":"00","desc":"Piper PA-28 181 Archer III"},"0AB":{"r":"N297ND","t":"PA44","f":"00","desc":""},"0BC":{"r":"N297NW","t":"RV8","f":"00","desc":"2003 WILSON DAVID L RV-8"},"0C1":{"r":"N297PA","t":"P28A","f":"00","desc":"2002 PIPER PA-28-181"},"0C4":{"r":"N297PD","t":"AS50","f":"01","desc":"AIRBUS HELICOPTERS INC AS350B2"},"0C6":{"r":"N297PF","t":"FA10","f":"00","desc":""},"0C9":{"r":"N297PJ","t":"GLF4","f":"00","desc":"GULFSTREAM AEROSPACE G-IV"},"0CC":{"r":"N297PM","t":"PA46","f":"00","desc":"1997 PIPER PA 46-350P"},"0CF":{"r":"N297PQ","t":"CRJ9","f":"00","desc":"2013 BOMBARDIER INC CL-600-2D24"},"0D1":{"r":"N297PS","t":"CRUZ","f":"00","desc":""},"0F4":{"r":"N297RB","t":"CH60","f":"00","desc":"Z\u00c3\u00a9nith Zenair Zodiac CH 601 XL"},"0F8":{"r":"N297RF","t":"PA11","f":"00","desc":"2013 CUBCRAFTERS INC CC11-160"},"106":{"r":"N297RV","t":"RV7","f":"00","desc":"2004 JENNINGS JOHN D RV-7A"},"10C":{"r":"N297SA","t":"DHC6","f":"00","desc":"DEHAVILLAND DHC-6-300"},"111":{"r":"N297SF","t":"GLEX","f":"00","desc":"Bombardier BD700 Global Express"},"115":{"r":"N297SK","t":"E135","f":"00","desc":"2001 EMBRAER EMB-135KL"},"119":{"r":"N297SP","t":"C172","f":"00","desc":"2003 CESSNA 172S"},"120":{"r":"N297SW","t":"E120","f":"00","desc":"1996 EMBRAER EMB-120ER"},"127":{"r":"N297TC","t":"C172","f":"00","desc":"Cessna 172R Skyhawk"},"132":{"r":"N297TP","t":"SR20","f":"00","desc":"Cirrus Design SR20"},"13A":{"r":"N297TX","t":"H25B","f":"00","desc":"2007 HAWKER BEECHCRAFT CORP HAWKER 900XP"},"153":{"r":"N297UX","t":"E120","f":"00","desc":"Embraer EMB-120 ER"},"16F":{"r":"N297W","t":"S92","f":"00","desc":"SIKORSKY S-92A"},"178":{"r":"N297WJ","t":"BE35","f":"00","desc":"Beech Bonanza P35"},"17C":{"r":"N297WN","t":"B737","f":"00","desc":"2007 BOEING 737-7H4"},"1D3":{"r":"N2970","t":"AS50","f":"00","desc":""},"1DB":{"r":"N2970H","t":"","f":"00","desc":"1946 ERCOUPE 415-C"},"1DC":{"r":"N2970J","t":"C150","f":"00","desc":"Cessna 150G"},"1E0":{"r":"N2970N","t":"P28B","f":"00","desc":"Piper PA-28 236 Dakota"},"1E5":{"r":"N2970T","t":"P28B","f":"00","desc":"1979 PIPER PA-28-236"},"1E6":{"r":"N2970U","t":"P28B","f":"00","desc":"Piper PA-28 236 Dakota"},"1F9":{"r":"N2971C","t":"C180","f":"00","desc":"Cessna 180"},"1FC":{"r":"N2971F","t":"C182","f":"00","desc":"Cessna 182J Skylane"},"201":{"r":"N2971L","t":"M20P","f":"00","desc":"1967 MOONEY M20C"},"203":{"r":"N2971N","t":"P28B","f":"00","desc":"1979 PIPER PA-28-236"},"216":{"r":"N29717","t":"B737","f":"00","desc":"1999 BOEING 737-724"},"21C":{"r":"N2972C","t":"P28A","f":"00","desc":"Piper PA-28 161 Warrior II"},"229":{"r":"N2972R","t":"P28R","f":"00","desc":"Piper PA-28R 200 Cherokee Arrow"},"246":{"r":"N2973K","t":"P28A","f":"00","desc":"PIPER PA-28-161"},"24C":{"r":"N2973R","t":"P28R","f":"00","desc":"1969 PIPER PA-28R-200"},"251":{"r":"N2973W","t":"P28A","f":"00","desc":"Piper PA-28 161 Warrior II"},"252":{"r":"N2973X","t":"P28A","f":"00","desc":"Piper PA-28 161 Warrior II"},"26C":{"r":"N2974N","t":"P28A","f":"00","desc":"1979 PIPER PA-28-181"},"271":{"r":"N2974T","t":"P28A","f":"00","desc":"Piper PA-28 181 Archer II"},"275":{"r":"N2974X","t":"","f":"00","desc":"BELLANCA 7ECA"},"28F":{"r":"N2975N","t":"C140","f":"00","desc":"Cessna 140"},"297":{"r":"N2975W","t":"BL8","f":"00","desc":"1980 BELLANCA 8KCAB"},"2B0":{"r":"N2976L","t":"M20P","f":"00","desc":"Mooney M.20C Mark 21"},"2CA":{"r":"N2977B","t":"BE35","f":"00","desc":"1955 BEECH F35"},"2D8":{"r":"N2977R","t":"P28R","f":"00","desc":"Piper PA-28R 200 Cherokee Arrow"},"2DC":{"r":"N2977V","t":"C150","f":"00","desc":"Cessna 150M"},"2F1":{"r":"N2978F","t":"C182","f":"00","desc":"Cessna 182J Skylane"},"2FB":{"r":"N2978R","t":"P28R","f":"00","desc":"1969 PIPER PA-28R-200"},"31E":{"r":"N2979R","t":"P28R","f":"00","desc":"1969 PIPER PA-28R-200"},"31F":{"r":"N2979S","t":"C411","f":"00","desc":"CESSNA 411A"},"333":{"r":"N298AA","t":"MD82","f":"00","desc":"McDonnell Douglas DC-9 82"},"335":{"r":"N298AC","t":"CH7B","f":"00","desc":"1999 AMERICAN CHAMPION AIRCRAFT 7GCBC"},"337":{"r":"N298AE","t":"SF34","f":"00","desc":""},"339":{"r":"N298AG","t":"H25B","f":"00","desc":"British Aerospace 125 800A"},"33E":{"r":"N298AM","t":"SR20","f":"00","desc":"Cirrus Design SR20"},"344":{"r":"N298AT","t":"P32R","f":"00","desc":"1998 PIPER PA-32R-301T"},"347":{"r":"N298AW","t":"UH1","f":"00","desc":""},"359":{"r":"N298BP","t":"GLST","f":"00","desc":"2008 BUILD A PLANE GLASAIR SPORTSMAN"},"367":{"r":"N298CC","t":"B06","f":"00","desc":""},"368":{"r":"N298CD","t":"SR20","f":"00","desc":"2002 CIRRUS DESIGN CORP SR20"},"36D":{"r":"N298CJ","t":"C25B","f":"00","desc":"2008 CESSNA 525B"},"36E":{"r":"N298CK","t":"LJ35","f":"00","desc":"Gates Learjet 35 A"},"375":{"r":"N298CS","t":"SR22","f":"00","desc":"2005 CIRRUS DESIGN CORP SR22"},"380":{"r":"N298DC","t":"R44","f":"00","desc":"Robinson R44 Raven II"},"383":{"r":"N298DF","t":"LNC4","f":"00","desc":"FINK DAVID B LANCAIR IV-P"},"38E":{"r":"N298DS","t":"DA40","f":"00","desc":"2008 DIAMOND AIRCRAFT IND INC DA 40"},"39C":{"r":"N298EF","t":"LJ60","f":"00","desc":"1997 LEARJET INC 60"},"3A9":{"r":"N298EU","t":"SR22","f":"00","desc":"Cirrus Design SR22"},"3B4":{"r":"N298FE","t":"B763","f":"00","desc":"2012 BOEING 767-32LF"},"3BB":{"r":"N298FM","t":"BE36","f":"00","desc":"Raytheon Aircraft Bonanza G36"},"3C9":{"r":"N298GA","t":"G150","f":"00","desc":""},"3CA":{"r":"N298GB","t":"C172","f":"00","desc":"Cessna 172N Skyhawk"},"3ED":{"r":"N298HM","t":"WW24","f":"00","desc":"1978 ISRAEL AIRCRAFT INDUSTRIES 1124"},"3EF":{"r":"N298HP","t":"P32R","f":"00","desc":"1998 PIPER PA-32R-301"},"3FC":{"r":"N298JB","t":"E190","f":"00","desc":"2009 EMBRAER ERJ 190-100 IGW"},"414":{"r":"N298KA","t":"BE9L","f":"00","desc":"Beechcraft Corp King Air C90GT"},"415":{"r":"N298KB","t":"SR22","f":"00","desc":"Cirrus Design SR22"},"42D":{"r":"N298LA","t":"AT8T","f":"00","desc":""},"448":{"r":"N298MC","t":"C172","f":"00","desc":"1997 CESSNA 172R"},"44A":{"r":"N298ME","t":"C172","f":"00","desc":"2000 CESSNA 172S"},"44C":{"r":"N298MG","t":"P28A","f":"00","desc":"Piper PA-28 181 Archer III"},"462":{"r":"N298ND","t":"PA44","f":"00","desc":"2001 PIPER PA-44-180"},"486":{"r":"N298PQ","t":"CRJ9","f":"00","desc":"2013 BOMBARDIER INC CL-600-2D24"},"48C":{"r":"N298PW","t":"P28A","f":"00","desc":"Piper PA-28 140 Cherokee"},"4A1":{"r":"N298QS","t":"F2TH","f":"00","desc":""},"4A2":{"r":"N298QT","t":"S92","f":"00","desc":"Sikorsky S-92 A"},"4A9":{"r":"N298R","t":"A109","f":"00","desc":"2004 AGUSTA SPA A109E"},"4AA":{"r":"N298RA","t":"GLST","f":"00","desc":"2010 AMMENTI DAVID A SPORTSMAN"},"4CC":{"r":"N298SK","t":"E145","f":"00","desc":"Embraer ERJ-145 LR"},"4D1":{"r":"N298SQ","t":"PA18","f":"00","desc":"Piper PA-18 95 Super Cub"},"4D7":{"r":"N298SW","t":"E120","f":"00","desc":"Embraer EMB-120 ER"},"4DE":{"r":"N298TC","t":"RV6","f":"00","desc":"1998 OLSON TOM C RV6-A"},"526":{"r":"N298W","t":"F900","f":"00","desc":"Dassault Falcon 900"},"527":{"r":"N298WA","t":"BE58","f":"00","desc":"2010 HAWKER BEECHCRAFT CORP G58"},"528":{"r":"N298WB","t":"H25B","f":"00","desc":"1984 BRITISH AEROSPACE BAE 125 SERIES 800A"},"533":{"r":"N298WN","t":"B737","f":"00","desc":"Boeing 737-7H4\/W"},"53F":{"r":"N298X","t":"M5","f":"00","desc":"Maule M-5 210C Rocket"},"548":{"r":"N298XJ","t":"H25B","f":"00","desc":""},"58B":{"r":"N2980A","t":"BE35","f":"00","desc":"Beech Bonanza V35B"},"593":{"r":"N2980J","t":"C150","f":"00","desc":"1966 CESSNA 150G"},"599":{"r":"N2980Q","t":"P32R","f":"00","desc":"PIPER PA-32R-300"},"59A":{"r":"N2980R","t":"P28R","f":"00","desc":"Piper PA-28R 200 Cherokee Arrow"},"5AD":{"r":"N2981","t":"GYRO","f":"00","desc":"Amateur Built Bensen Gyrocopter B.8M"},"5B2":{"r":"N2981E","t":"C172","f":"00","desc":"Cessna 172N Skyhawk"},"5B7":{"r":"N2981K","t":"C180","f":"00","desc":"Cessna 180K Skywagon 180"},"5D1":{"r":"N2982A","t":"C180","f":"00","desc":"Cessna 180"},"5DC":{"r":"N2982M","t":"P28R","f":"00","desc":"1977 PIPER PA-28R-201T"},"5F5":{"r":"N2983B","t":"","f":"00","desc":"BEECH D35"},"605":{"r":"N2983T","t":"M200","f":"00","desc":"1966 AERO COMMANDER 200D"},"637":{"r":"N29848","t":"","f":"00","desc":"1941 TAYLORCRAFT BF"},"643":{"r":"N2985K","t":"C180","f":"00","desc":"1980 CESSNA 180K"},"644":{"r":"N2985L","t":"M20P","f":"00","desc":"1967 MOONEY M20F"},"661":{"r":"N2986E","t":"C182","f":"00","desc":"1982 CESSNA 182R"},"664":{"r":"N2986H","t":"","f":"00","desc":"1946 ENGINEERING & RESEARCH 415-C"},"666":{"r":"N2986K","t":"C180","f":"00","desc":"1980 CESSNA 180K"},"66C":{"r":"N2986R","t":"P28R","f":"00","desc":"Piper PA-28R 200 Cherokee Arrow"},"682":{"r":"N2987C","t":"C180","f":"00","desc":"Cessna 180"},"684":{"r":"N2987E","t":"CH7A","f":"00","desc":"Aeronca Champion 7AC"},"692":{"r":"N2987U","t":"C172","f":"00","desc":"Cessna 172E Skyhawk"},"6AE":{"r":"N2988M","t":"PA32","f":"00","desc":"Piper PA-32 300 Cherokee Six"},"6B4":{"r":"N2988T","t":"M200","f":"00","desc":"1966 AERO COMMANDER 200D"},"6D1":{"r":"N2989M","t":"PA32","f":"00","desc":"1977 PIPER PA-32-300"},"6D7":{"r":"N2989T","t":"M200","f":"00","desc":"1966 AERO COMMANDER 200D"},"6EE":{"r":"N299AE","t":"B06","f":"00","desc":"1981 BELL HELICOPTER TEXTRON 206L-1"},"6F0":{"r":"N299AG","t":"M20P","f":"00","desc":"2000 MOONEY M20R"},"6F3":{"r":"N299AK","t":"BE20","f":"00","desc":""},"6F4":{"r":"N299AL","t":"BE20","f":"00","desc":"Raytheon Aircraft Company King Air B200"},"6F5":{"r":"N299AM","t":"PC12","f":"00","desc":"1998 PILATUS PC-12\/45"},"6FA":{"r":"N299AS","t":"B350","f":"00","desc":"Raytheon Aircraft Company King Air B350"},"6FB":{"r":"N299AT","t":"SR20","f":"00","desc":"2015 CIRRUS DESIGN CORP SR20"},"6FD":{"r":"N299AV","t":"BE20","f":"00","desc":"1999 RAYTHEON AIRCRAFT COMPANY B200"},"706":{"r":"N299BD","t":"BE36","f":"00","desc":"RAYTHEON AIRCRAFT COMPANY A36"},"709":{"r":"N299BG","t":"BE33","f":"00","desc":"1989 BEECH F33A"},"71F":{"r":"N299CD","t":"SR20","f":"00","desc":"2002 CIRRUS DESIGN CORP SR20"},"722":{"r":"N299CG","t":"S22T","f":"00","desc":"2014 CIRRUS DESIGN CORP SR22T"},"723":{"r":"N299CH","t":"RV9","f":"00","desc":"2005 HANES ROBERT E RV9A"},"72B":{"r":"N299CR","t":"CH75","f":"00","desc":"Zenith Zenair STOL CH 750"},"72C":{"r":"N299CS","t":"C525","f":"00","desc":""},"72D":{"r":"N299CT","t":"FDCT","f":"00","desc":"2006 FLIGHT DESIGN GMBH CTSW"},"730":{"r":"N299CW","t":"C525","f":"00","desc":"1997 CESSNA 525"},"731":{"r":"N299CX","t":"C750","f":"00","desc":"2009 CESSNA 750"},"733":{"r":"N299CZ","t":"BE99","f":"00","desc":"1969 BEECH 99"},"736":{"r":"N299DB","t":"C56X","f":"00","desc":"2009 CESSNA 560XL"},"73C":{"r":"N299DH","t":"C560","f":"00","desc":"Cessna Citation Encore"},"742":{"r":"N299DP","t":"FA10","f":"00","desc":"Dassault Falcon 10"},"750":{"r":"N299EC","t":"SW3","f":"00","desc":"SWEARINGEN SA226-T(B)"},"752":{"r":"N299EE","t":"DHC2","f":"00","desc":"1954 DEHAVILLAND BEAVER DHC-2 MK.1"},"769":{"r":"N299FC","t":"P32R","f":"00","desc":"Piper PA-32R 301 Saratoga SP"},"781":{"r":"N299GB","t":"C421","f":"00","desc":"Cessna 421C Golden Eagle"},"790":{"r":"N299GS","t":"H25A","f":"00","desc":""},"79D":{"r":"N299HE","t":"R44","f":"00","desc":"1999 ROBINSON HELICOPTER R44"},"7B4":{"r":"N299JC","t":"FA20","f":"00","desc":"1974 DASSAULT\/SUD FAN JET FALCON SER F"},"7BD":{"r":"N299JM","t":"H25B","f":"00","desc":"2005 RAYTHEON AIRCRAFT COMPANY HAWKER 800XP"},"7BF":{"r":"N299JP","t":"DA40","f":"00","desc":"2003 DIAMOND AIRCRAFT IND INC DA 40"},"7C2":{"r":"N299JS","t":"P28A","f":"00","desc":"1974 PIPER PA-28-151"},"7C6":{"r":"N299JW","t":"SR22","f":"00","desc":"Cirrus Design SR22"},"7D3":{"r":"N299KJ","t":"H269","f":"00","desc":""},"7D8":{"r":"N299KP","t":"BE9T","f":"00","desc":"Beech King Air F90-1"},"7DA":{"r":"N299KR","t":"CL60","f":"00","desc":"2008 BOMBARDIER INC CL-600-2B16"},"7DC":{"r":"N299KT","t":"LNC4","f":"00","desc":"1996 LARUE CARL LANCAIR"},"7E3":{"r":"N299L","t":"LEG2","f":"00","desc":"2009 MALLECK GRIFF H LEGACY"},"7FD":{"r":"N299MA","t":"P46T","f":"00","desc":"2007 PIPER AIRCRAFT INC PA46-500TP"},"7FF":{"r":"N299MC","t":"C206","f":"00","desc":"2014 CESSNA T206H"},"803":{"r":"N299MG","t":"S22T","f":"00","desc":"Cirrus Design SR22T"},"806":{"r":"N299MK","t":"BE20","f":"00","desc":"Beech King Air B200"},"80A":{"r":"N299MP","t":"SR22","f":"00","desc":"Cirrus Design SR22"},"80C":{"r":"N299MR","t":"SR22","f":"00","desc":"Cirrus Design SR22"},"810":{"r":"N299MV","t":"FA50","f":"00","desc":""},"819":{"r":"N299ND","t":"PA44","f":"00","desc":"2001 PIPER PA-44-180"},"82F":{"r":"N299PA","t":"P28A","f":"00","desc":"1999 PIPER PA-28-181"},"83C":{"r":"N299PP","t":"E50P","f":"00","desc":"2010 EMBRAER-EMPRESA BRASILEIRA DE EMB-500"},"83D":{"r":"N299PQ","t":"CRJ9","f":"00","desc":"Canadair CRJ900 Regional Jet"},"83E":{"r":"N299PR","t":"FA5X","f":"00","desc":"2000 DASSAULT AVIATION MYSTERE-FALCON 50"},"83F":{"r":"N299PS","t":"G200","f":"00","desc":"Gulfstream Aerospace G200"},"840":{"r":"N299PT","t":"C182","f":"00","desc":"1969 CESSNA 182M"},"863":{"r":"N299RC","t":"BE9L","f":"00","desc":"2007 RAYTHEON AIRCRAFT COMPANY C90GT"},"866":{"r":"N299RF","t":"","f":"00","desc":"2008 FIELD WAYNE A RV9A"},"86A":{"r":"N299RK","t":"C55B","f":"00","desc":"2002 CESSNA 550"},"86C":{"r":"N299RM","t":"PA27","f":"00","desc":"Piper PA-23 Aztec 250F"},"86E":{"r":"N299RP","t":"BE9L","f":"00","desc":"1996 RAYTHEON AIRCRAFT COMPANY C90A"},"870":{"r":"N299RR","t":"PA11","f":"00","desc":"2014 RICHARD D RIDER CCK-1865"},"87C":{"r":"N299SC","t":"GLF4","f":"00","desc":"2013 GULFSTREAM AEROSPACE GIV-X (G450)"},"883":{"r":"N299SK","t":"E135","f":"00","desc":""},"887":{"r":"N299SP","t":"C206","f":"00","desc":"2007 CESSNA T206H"},"889":{"r":"N299SR","t":"SR20","f":"00","desc":"2007 CIRRUS DESIGN CORP SR20"},"88E":{"r":"N299SW","t":"E120","f":"00","desc":"Embraer EMB-120 ER"},"894":{"r":"N299TB","t":"B06","f":"00","desc":"1980 BELL 206B"},"8C1":{"r":"N299UX","t":"E120","f":"00","desc":"Embraer EMB-120 ER"},"8D0":{"r":"N299VM","t":"BE9L","f":"00","desc":"Beech King Air C90A"},"8DD":{"r":"N299W","t":"BE36","f":"00","desc":"RAYTHEON AIRCRAFT COMPANY A36"},"8DF":{"r":"N299WB","t":"H25A","f":"00","desc":"1980 BRITISH AEROSPACE HS 125-700A"},"8E3":{"r":"N299WF","t":"A109","f":"00","desc":""},"8EA":{"r":"N299WN","t":"B737","f":"00","desc":"BOEING 737-7H4"},"8F6":{"r":"N299X","t":"","f":"00","desc":"2011 AEROPRO CZ A240"},"928":{"r":"N299Z","t":"BE18","f":"00","desc":"Beech 18 E \/ S"},"954":{"r":"N2990U","t":"C172","f":"00","desc":"Cessna 172E Skyhawk"},"95E":{"r":"N29904","t":"WACF","f":"00","desc":"Weaver Aircraft Company Waco ZPF-7"},"960":{"r":"N29906","t":"E145","f":"00","desc":"2001 EMBRAER EMB-145LR"},"961":{"r":"N29907","t":"B788","f":"00","desc":"2013 BOEING 787-8"},"965":{"r":"PT-FMW","t":"C310","f":"00","desc":"Cessna 310R"},"969":{"r":"N2991E","t":"CH7A","f":"00","desc":"1946 AERONCA 7DC"},"970":{"r":"N2991M","t":"PA12","f":"00","desc":"PIPER PA-12"},"976":{"r":"N2991T","t":"M200","f":"00","desc":"1966 AERO COMMANDER 200D"},"97E":{"r":"N29911","t":"WACF","f":"00","desc":"1940 WACO UPF-7"},"984":{"r":"N29917","t":"E145","f":"00","desc":"Embraer ERJ145LR"},"99C":{"r":"N2992W","t":"CH75","f":"00","desc":"DRUMHELLER KENNETH G ZENITH CH 750"},"99D":{"r":"N2992X","t":"COL4","f":"00","desc":""},"9A3":{"r":"N29923","t":"WACF","f":"00","desc":"1940 WACO UPF-7"},"9B2":{"r":"N2993H","t":"","f":"00","desc":"1946 ENGINEERING & RESEARCH 415-D"},"9BC":{"r":"N2993T","t":"M200","f":"00","desc":"1967 AERO COMMANDER 200D"},"9C0":{"r":"N2993X","t":"C177","f":"00","desc":"Cessna 177"},"9C6":{"r":"N29933","t":"T6","f":"00","desc":"1951 NORTH AMERICAN AT-6G"},"9CE":{"r":"N2994A","t":"C180","f":"00","desc":"Cessna 180"},"9D1":{"r":"N2994D","t":"C170","f":"00","desc":"1955 CESSNA 170B"},"9DD":{"r":"N2994R","t":"P28R","f":"00","desc":"Piper PA-28R 200 Cherokee Arrow"},"9E7":{"r":"N29941","t":"T6","f":"00","desc":""},"9F6":{"r":"N2995F","t":"C182","f":"00","desc":"Cessna 182J Skylane"},"A00":{"r":"N2995R","t":"P28R","f":"00","desc":"1969 PIPER PA-28R-200"},"A0E":{"r":"N29955","t":"WACF","f":"00","desc":"WACO UPF-7"},"A12":{"r":"N29959","t":"BE36","f":"00","desc":"1986 BEECH A36"},"A1A":{"r":"N2996G","t":"CH7A","f":"00","desc":"1967 CHAMPION 7ECA"},"A2A":{"r":"N2996Y","t":"C182","f":"00","desc":"1962 CESSNA 182E"},"A2D":{"r":"N29961","t":"B789","f":"00","desc":"Boeing 787-9"},"A33":{"r":"N29967","t":"WACF","f":"00","desc":"1940 WACO UPF-7"},"A34":{"r":"N29968","t":"B789","f":"00","desc":"Boeing 787 9"},"A5F":{"r":"N2998F","t":"C182","f":"00","desc":"1966 CESSNA 182J"},"A65":{"r":"N2998M","t":"BE33","f":"00","desc":"Beech Bonanza F33A"},"A7C":{"r":"N2999","t":"","f":"00","desc":"1973 ANDERSEN PITTS S-1S"},"A85":{"r":"N2999J","t":"SR22","f":"00","desc":"2003 CIRRUS DESIGN CORP SR22"},"A88":{"r":"N2999M","t":"BE33","f":"00","desc":"1985 BEECH F33A"},"A9C":{"r":"N29997","t":"BE20","f":"00","desc":"Beech King Air B200"},"A9F":{"r":"N3","t":"C56X","f":"01","desc":"560XL"},"AA0":{"r":"N3A","t":"SHIP","f":"00","desc":""},"AA8":{"r":"N3AH","t":"BE30","f":"00","desc":"Beech King Air 300"},"AAA":{"r":"N3AK","t":"PA18","f":"00","desc":"Turbine Cubs of Wyoming PA-18 Super Cub"},"AAC":{"r":"N3AM","t":"M20P","f":"00","desc":"1966 MOONEY M20E"},"AB1":{"r":"N3AS","t":"LJ45","f":"00","desc":"2011 LEARJET INC 45"},"AB5":{"r":"N3AW","t":"B350","f":"00","desc":"RAYTHEON AIRCRAFT COMPANY B300"},"AB9":{"r":"N3B","t":"C750","f":"00","desc":"2002 CESSNA 750"},"ABD":{"r":"N3BD","t":"C182","f":"00","desc":"1979 CESSNA 182Q"},"AC5":{"r":"N3BM","t":"FA5X","f":"00","desc":"Dassault Falcon 50EX"},"AC9":{"r":"N3BR","t":"BE35","f":"00","desc":"1973 BEECH V35B"},"ACB":{"r":"N3BT","t":"PA31","f":"00","desc":"1977 PIPER PA-31-350"},"ACD":{"r":"N3BV","t":"M20P","f":"00","desc":"1975 MOONEY M20F"},"ACE":{"r":"N3BW","t":"BE35","f":"00","desc":"1976 BEECH V35B"},"AE0":{"r":"N3CP","t":"GLF6","f":"00","desc":"Gulfstream Aerospace G650 ER"},"AE2":{"r":"N3CR","t":"B350","f":"00","desc":"Beech King Air B350"},"AE4":{"r":"N3CT","t":"C25B","f":"00","desc":"2005 CESSNA 525B"},"AE5":{"r":"N3CU","t":"P337","f":"00","desc":"Cessna P337G Pressurized Skymaster"},"AE6":{"r":"N3CV","t":"P46T","f":"00","desc":"2009 PIPER AIRCRAFT INC PA46-500TP"},"AE8":{"r":"N3CX","t":"PA46","f":"00","desc":"Piper PA-46 350P Malibu Mirage"},"AEB":{"r":"N3D","t":"B06","f":"00","desc":"2007 BELL 206B"},"AEC":{"r":"N3DA","t":"BE36","f":"00","desc":"1997 RAYTHEON AIRCRAFT COMPANY A36"},"AF0":{"r":"N3DE","t":"E145","f":"00","desc":"2002 EMBRAER EMB-145LR"},"AF9":{"r":"N3DP","t":"GLF3","f":"00","desc":"Gulfstream III"},"AFA":{"r":"N3DQ","t":"C414","f":"00","desc":"1970 CESSNA 414"},"AFD":{"r":"N3DT","t":"PA18","f":"00","desc":"Piper PA-18 150 Super Cub"},"B00":{"r":"N3DW","t":"C182","f":"00","desc":"Cessna 182P Skylane"},"B01":{"r":"N3DX","t":"BE35","f":"00","desc":"1973 BEECH V35B"},"B07":{"r":"N3EC","t":"GLAS","f":"00","desc":"COVINGTON EDWARD L SHA-GLASAIR"},"B0E":{"r":"N3EK","t":"TBM8","f":"00","desc":"2010 SOCATA TBM 700"},"B0F":{"r":"N3EL","t":"C340","f":"00","desc":"1978 CESSNA 340A"},"B10":{"r":"N3EM","t":"P210","f":"00","desc":"1981 CESSNA P210N"},"B1A":{"r":"N3EX","t":"GLAS","f":"00","desc":"MCEVOY MAURICE B GLASAIR III"},"B1E":{"r":"N3FA","t":"C560","f":"00","desc":"1989 CESSNA 560"},"B1F":{"r":"N3FB","t":"G280","f":"00","desc":"IAI LTD GULFSTREAM G280"},"B21":{"r":"N3FD","t":"ASTR","f":"00","desc":"Gulfstream Aerospace G100"},"B22":{"r":"N3FE","t":"CL60","f":"00","desc":"2007 BOMBARDIER INC CL-600-2B16"},"B2A":{"r":"N3FN","t":"PA32","f":"00","desc":"1974 PIPER PA-32-260"},"B2B":{"r":"N3FP","t":"RV6","f":"00","desc":"2015 JAY PEARLMAN RV6A"},"B2C":{"r":"N3FQ","t":"GLID","f":"00","desc":"2003 ALISPORT SRL SILENT-IN"},"B2E":{"r":"N3FS","t":"G150","f":"00","desc":"2008 ISRAEL AEROSPACE INDUSTRIESLTD GULFSTREAM G150"},"B35":{"r":"N3FZ","t":"PTS1","f":"00","desc":"Amateur Built Pitts Special S-1S"},"B39":{"r":"N3GC","t":"BE9L","f":"01","desc":"Beech C90 King Air"},"B41":{"r":"N3GL","t":"LA4","f":"00","desc":""},"B43":{"r":"N3GN","t":"C501","f":"00","desc":"Cessna 501 Citation 1SP"},"B45":{"r":"N3GQ","t":"DA42","f":"00","desc":"2006 DIAMOND AIRCRAFT IND GMBH DA 42"},"B47":{"r":"N3GS","t":"TBM8","f":"00","desc":"Socata TBM850"},"B48":{"r":"N3GT","t":"MU2","f":"00","desc":"MITSUBISHI MU-2B-25"},"B49":{"r":"XA-RYM","t":"H25B","f":"00","desc":"British Aerospace 125 800A"},"B4F":{"r":"N3H","t":"GLF4","f":"00","desc":"1990 GULFSTREAM AEROSPACE G-IV"},"B51":{"r":"N3HB","t":"F900","f":"00","desc":"1993 DASSAULT-BREGUET MYSTERE FALCON 900"},"B53":{"r":"N3HD","t":"C240","f":"00","desc":"Cessna T240 Corvalis"},"B54":{"r":"N3HE","t":"BE55","f":"00","desc":"Beech Baron B55"},"B59":{"r":"N3HK","t":"C340","f":"00","desc":"1975 CESSNA 340"},"B5E":{"r":"N3HQ","t":"C172","f":"00","desc":"CESSNA 172N"},"B67":{"r":"N3HZ","t":"R66","f":"00","desc":"ROBINSON HELICOPTER CO R66"},"B69":{"r":"N3JA","t":"C172","f":"00","desc":"1975 CESSNA 172M"},"B74":{"r":"N3JM","t":"C56X","f":"00","desc":"2006 CESSNA 525B"},"B76":{"r":"N3JP","t":"C182","f":"00","desc":"Cessna 182Q Skylane"},"B7C":{"r":"N3JV","t":"NIMB","f":"00","desc":"1972 SCHEMPP-HIRTH K. G NIMBUS II"},"B7E":{"r":"N3JX","t":"C170","f":"00","desc":"Cessna 170B"},"B80":{"r":"N3JZ","t":"CH7A","f":"00","desc":"Champion Tri-Traveler 7FC"},"B81":{"r":"N3K","t":"PRM1","f":"00","desc":"Beech 390 Premier 1A"},"B87":{"r":"N3KF","t":"BE9L","f":"00","desc":""},"B8D":{"r":"N3KM","t":"","f":"00","desc":"1965 MOONEY M20C"},"B8E":{"r":"N3KN","t":"BE36","f":"00","desc":"1980 BEECH A36"},"B8F":{"r":"N3KP","t":"P210","f":"00","desc":"1981 CESSNA P210N"},"B90":{"r":"N3KQ","t":"PA11","f":"00","desc":"2014 CUBCRAFTERS INC CC11-160"},"B97":{"r":"N3KX","t":"C414","f":"00","desc":"Cessna 414"},"B98":{"r":"N3KY","t":"B06","f":"00","desc":"BELL 206L-3"},"B9B":{"r":"N3LA","t":"PA31","f":"00","desc":"Piper PA-31 350 Navajo Chieftain"},"BA0":{"r":"N3LF","t":"PC12","f":"00","desc":"2010 PILATUS AIRCRAFT LTD PC-12\/47E"},"BA2":{"r":"N3LH","t":"GLF2","f":"00","desc":"Grumman GII"},"BA7":{"r":"N3LN","t":"C340","f":"00","desc":"Cessna 340"},"BAB":{"r":"N3LS","t":"BE9L","f":"00","desc":"1977 BEECH E-90"},"BAD":{"r":"N3LU","t":"C182","f":"00","desc":"Cessna 182P Skylane"},"BB3":{"r":"N3M","t":"GLF5","f":"00","desc":"2010 GULFSTREAM AEROSPACE GV-SP (G550)"},"BB4":{"r":"N3MA","t":"MU2","f":"00","desc":"Mitsubishi MU-2 Marquise"},"BB6":{"r":"N3MC","t":"EC45","f":"00","desc":"Airbus Helicopters EC145 T2"},"BBD":{"r":"N3MK","t":"C77R","f":"00","desc":"Cessna 177 Cardinal RG"},"BC5":{"r":"N3MT","t":"EA50","f":"00","desc":"2008 ECLIPSE AVIATION CORP EA500"},"BC6":{"r":"N3MU","t":"BE58","f":"00","desc":"Beech Baron 58"},"BCF":{"r":"N3NC","t":"BE20","f":"00","desc":"2007 HAWKER BEECHCRAFT CORP B200"},"BD5":{"r":"N3NJ","t":"A139","f":"01","desc":"AGUSTAWESTLAND PHILADELPHIA AW139"},"BDF":{"r":"N3NU","t":"RV3","f":"00","desc":"2009 NYSTROM JOHN L JR RV-3B"},"BE5":{"r":"N3P","t":"RV12","f":"00","desc":"VANS AIRCRAFT INC RV-12"},"BE6":{"r":"N3PA","t":"C172","f":"00","desc":"Cessna 172K Skyhawk"},"BE8":{"r":"N3PC","t":"GLEX","f":"00","desc":"2000 BOMBARDIER INC BD-700-1A10"},"BE9":{"r":"N3PD","t":"EC45","f":"01","desc":"EUROCOPTER DEUTSCHLAND GMBH MBB-BK 117 C-2"},"BEA":{"r":"N3PE","t":"BE58","f":"00","desc":"1977 BEECH 58"},"BEB":{"r":"N3PF","t":"BE55","f":"00","desc":"Beech Baron A55"},"BEC":{"r":"N3PG","t":"GLF5","f":"00","desc":"2005 GULFSTREAM AEROSPACE GV-SP (G550)"},"BEE":{"r":"N3PJ","t":"VEZE","f":"00","desc":"1990 KAIRIS PETER JR VARI EZE"},"BF6":{"r":"N3PS","t":"LA4","f":"00","desc":"CONSOLIDATED AERONAUTICS INC. LAKE LA-4-200"},"BFB":{"r":"N3PX","t":"BE20","f":"00","desc":"1984 BEECH B200"},"BFC":{"r":"N3PY","t":"DHC6","f":"00","desc":"De Havilland Canada DHC-6 Twin Otter 310"},"BFD":{"r":"N3PZ","t":"C210","f":"00","desc":"Cessna 210N Centurion"},"BFF":{"r":"N3QA","t":"BE36","f":"00","desc":"1984 BEECH B36TC"},"C00":{"r":"N3QB","t":"ZZZZ","f":"00","desc":"2011 BRAND RICHARD J PROTEA"},"C03":{"r":"N3QE","t":"C510","f":"00","desc":"2009 CESSNA 510"},"C05":{"r":"N3QG","t":"H25B","f":"00","desc":"BRITISH AEROSPACE BAE 125 SERIES 800A"},"C06":{"r":"N3QH","t":"R44","f":"00","desc":"Robinson R44 Raven II"},"C0C":{"r":"N3QP","t":"QIC2","f":"00","desc":"DWYER MICHAEL D Q-200"},"C0D":{"r":"N3QQ","t":"P32R","f":"00","desc":"1976 PIPER PA-32R-300"},"C10":{"r":"N3QT","t":"M20P","f":"00","desc":"Mooney M.20E Super 21"},"C11":{"r":"N3QU","t":"LNC2","f":"00","desc":"2007 QUINN MARK J LANCAIR 320\/360"},"C13":{"r":"N3QW","t":"RV7","f":"00","desc":"Mccaw Denny Vans Rv-7A"},"C15":{"r":"N3QY","t":"B06","f":"00","desc":""},"C16":{"r":"N3QZ","t":"C182","f":"00","desc":"Cessna 182P Skylane"},"C18":{"r":"N3RA","t":"C182","f":"00","desc":"Cessna 182Q Skylane"},"C1A":{"r":"N3RC","t":"C25C","f":"00","desc":"2011 CESSNA 525C"},"C21":{"r":"N3RK","t":"PAY2","f":"00","desc":"1981 PIPER PA-31T2"},"C25":{"r":"N3RP","t":"CL60","f":"00","desc":""},"C29":{"r":"N3RT","t":"SX30","f":"00","desc":"TEWS K RICHARD SWEARINGEN SX300"},"C2C":{"r":"N3RW","t":"C172","f":"00","desc":"1978 CESSNA 172N"},"C2E":{"r":"N3RY","t":"C208","f":"00","desc":""},"C2F":{"r":"N3RZ","t":"M20T","f":"00","desc":"1993 MOONEY M20M"},"C31":{"r":"N3SA","t":"GLF4","f":"00","desc":""},"C36":{"r":"N3SF","t":"C172","f":"00","desc":"Cessna 172L Skyhawk"},"C3B":{"r":"N3SL","t":"C182","f":"00","desc":"Cessna 182L Skylane"},"C3C":{"r":"N3SM","t":"C180","f":"00","desc":"1964 CESSNA 180H"},"C3E":{"r":"N3SP","t":"PAY4","f":"00","desc":"Piper PA-42-1000 Cheyenne IV"},"C47":{"r":"N3SY","t":"M20P","f":"00","desc":"1967 MOONEY M20E"},"C48":{"r":"N3SZ","t":"GLAS","f":"00","desc":"Stoddard-Hamilton Glasair III"},"C4C":{"r":"N3TC","t":"C208","f":"00","desc":"2011 CESSNA 208"},"C4E":{"r":"N3TE","t":"GLID","f":"00","desc":"CENTRAIR 101A"},"C51":{"r":"N3TH","t":"BE55","f":"00","desc":"1967 BEECH 95-B55 (T42A)"},"C55":{"r":"N3TM","t":"J3","f":"00","desc":"Piper J-3 C-65 Cub"},"C56":{"r":"N3TN","t":"C172","f":"00","desc":"Cessna 172M Skyhawk"},"C58":{"r":"N3TQ","t":"C310","f":"00","desc":"1973 CESSNA 310Q"},"C5A":{"r":"N3TS","t":"LNC4","f":"00","desc":"Lancair International Lancair IV P"},"C60":{"r":"N3TY","t":"BE55","f":"00","desc":"1975 BEECH E-55"},"C6A":{"r":"N3UH","t":"LEG2","f":"00","desc":"2007 LONG GLENN E LEGACY FG"},"C6F":{"r":"N3UN","t":"PA24","f":"00","desc":"Piper PA-24 260 Comanche B"},"C76":{"r":"N3UV","t":"AC50","f":"00","desc":"1973 AERO COMMANDER 500 S"},"C77":{"r":"N3UW","t":"P28B","f":"00","desc":"1964 PIPER PA-28-235"},"C78":{"r":"N3UX","t":"C182","f":"00","desc":"Cessna 182Q Skylane"},"C79":{"r":"N3UY","t":"COL4","f":"00","desc":"2008 CESSNA AIRCRAFT CO LC41-550FG"},"C7A":{"r":"N3UZ","t":"C340","f":"00","desc":"1982 CESSNA 340A"},"C7C":{"r":"N3VA","t":"C414","f":"00","desc":"CESSNA 414"},"C7D":{"r":"N3VB","t":"C320","f":"00","desc":"1965 CESSNA 320D"},"C7E":{"r":"N3VC","t":"C82R","f":"00","desc":"1980 CESSNA R182"},"C81":{"r":"N3VF","t":"FA5X","f":"00","desc":"1997 DASSAULT MYSTERE FALCON 50EX"},"C84":{"r":"N3VJ","t":"LJ31","f":"00","desc":"1991 LEARJET INC 31A"},"C88":{"r":"N3VN","t":"BE33","f":"00","desc":"Beech Bonanza F33A"},"C8F":{"r":"N3VV","t":"BE58","f":"00","desc":"2004 VOGEL DAVID WH6P"},"C94":{"r":"N3W","t":"A139","f":"00","desc":"2009 AGUSTA AEROSPACE CORP AW139"},"C96":{"r":"N3WB","t":"EVOT","f":"00","desc":"2013 EVO13 LLC LANCAIR EVOLUTION"},"C9D":{"r":"N3WJ","t":"BE55","f":"00","desc":"1974 BEECH 95-B55 (T42A)"},"C9E":{"r":"N3WK","t":"BE55","f":"00","desc":"1963 BEECH 95-B55 (T42A)"},"CA3":{"r":"N3WQ","t":"CA8","f":"00","desc":"Comp Air 8"},"CA5":{"r":"N3WS","t":"C25B","f":"00","desc":"2007 CESSNA 525B"},"CA6":{"r":"N3WT","t":"C501","f":"00","desc":"1979 CESSNA 501"},"CA8":{"r":"N3WV","t":"","f":"00","desc":"2006 BELL 407"},"CA9":{"r":"N3WW","t":"C182","f":"00","desc":"Cessna 182Q Skylane"},"CAD":{"r":"N3X","t":"RV4","f":"00","desc":"Vans RV-4"},"CAF":{"r":"N3XB","t":"BE9L","f":"00","desc":"1967 BEECH 65-A90"},"CB1":{"r":"N3XD","t":"ZZZZ","f":"00","desc":"1996 WHEELER K\/WHEELER C WHEELER FOUR"},"CB3":{"r":"N3XF","t":"EPIC","f":"00","desc":"Epic Aircraft Company Epic LT"},"CBF":{"r":"N3XT","t":"BE35","f":"00","desc":"1970 BEECH V35B"},"CC4":{"r":"N3XY","t":"LNC4","f":"00","desc":"2013 STRATTON BRUCE LANCAIR IV"},"CC9":{"r":"N3YC","t":"PA11","f":"00","desc":"CubCrafters CC11 160"},"CCB":{"r":"N3YE","t":"C172","f":"00","desc":"Cessna 172N Skyhawk"},"CCC":{"r":"N3YF","t":"M20P","f":"00","desc":"1982 MOONEY M20J"},"CD2":{"r":"N3YM","t":"GLAS","f":"00","desc":"2001 HANSON FREDERICK A GLASAIR III"},"CD9":{"r":"N3YU","t":"C182","f":"00","desc":"2004 CESSNA 182T"},"CDA":{"r":"ZS-PKB","t":"B190","f":"00","desc":""},"CDE":{"r":"N3YZ","t":"TLEG","f":"00","desc":"2000 ZOCHOL RICHARD L TURBINE LEGEND"},"CDF":{"r":"N3Z","t":"M20P","f":"00","desc":"Mooney M.20E Chaparral"},"CE2":{"r":"N3ZC","t":"C680","f":"00","desc":"Cessna Citation Sovereign"},"CE6":{"r":"N3ZG","t":"SR22","f":"00","desc":"Cirrus Design SR22"},"CEF":{"r":"N3ZR","t":"C172","f":"00","desc":"Reims\/Cessna F172M"},"CF6":{"r":"N3ZY","t":"GLST","f":"00","desc":"2005 TILLION CLEMENT VINCENT III SPORTSMAN GS-2"},"CF7":{"r":"N3ZZ","t":"DA40","f":"00","desc":"2007 DIAMOND AIRCRAFT IND INC DA 40"},"CFB":{"r":"N30AB","t":"WACF","f":"00","desc":"Waco Classic Aircraft Waco YMF-5C"},"CFD":{"r":"N30AD","t":"C25A","f":"00","desc":"2003 CESSNA 525A"},"CFE":{"r":"N30AE","t":"BE50","f":"00","desc":"1962 BEECH J50"},"D08":{"r":"N30AQ","t":"C525","f":"00","desc":"1999 CESSNA 525"},"D0E":{"r":"N30AW","t":"C185","f":"00","desc":"1974 CESSNA A185F"},"D1A":{"r":"N30BH","t":"B407","f":"00","desc":""},"D1D":{"r":"N30BL","t":"SONX","f":"00","desc":""},"D1F":{"r":"N30BN","t":"BE58","f":"00","desc":""},"D20":{"r":"N30BP","t":"C525","f":"00","desc":"Cessna 525 Citation M2"},"D2A":{"r":"N30BZ","t":"CL30","f":"00","desc":""},"D2C":{"r":"N30CA","t":"BE33","f":"00","desc":"1974 BEECH F33A"},"D38":{"r":"N30CN","t":"BE9L","f":"00","desc":""},"D3F":{"r":"N30CV","t":"BE9L","f":"00","desc":"Beech E90 King Air"},"D41":{"r":"N30CX","t":"P46T","f":"00","desc":"2008 PIPER AIRCRAFT INC PA46-500TP"},"D4A":{"r":"N30DF","t":"PA31","f":"00","desc":"1974 PIPER PA-31-310"},"D50":{"r":"N30DM","t":"BE36","f":"00","desc":"Beech Bonanza A36"},"D54":{"r":"N30DR","t":"PA31","f":"00","desc":"Piper PA-31 325 Navajo C\/R"},"D57":{"r":"N30DU","t":"PAY1","f":"00","desc":"1978 PIPER PA-31T"},"D5E":{"r":"N30EA","t":"DHC6","f":"00","desc":"De Havilland Canada DHC-6 Twin Otter 200"},"D61":{"r":"N30ED","t":"BE35","f":"00","desc":"Beech Bonanza V35B"},"D62":{"r":"N30EE","t":"C414","f":"00","desc":"1979 CESSNA 414A"},"D63":{"r":"N30EF","t":"C172","f":"00","desc":"Cessna 172Q Cutlass"},"D64":{"r":"N30EG","t":"M20P","f":"00","desc":"MOONEY M20E"},"D65":{"r":"N30EH","t":"A109","f":"00","desc":"Agusta A109E"},"D71":{"r":"N30EV","t":"M20T","f":"00","desc":"Mooney M.20K Model 231"},"D72":{"r":"N30EW","t":"C210","f":"00","desc":"210L"},"D78":{"r":"N30FB","t":"C414","f":"00","desc":"1978 CESSNA 414A"},"D79":{"r":"N30FC","t":"C82R","f":"00","desc":"Cessna R182 Skylane RG"},"D7A":{"r":"N30FD","t":"A109","f":"00","desc":"Agusta A.109 C"},"D7E":{"r":"N30FH","t":"PA34","f":"00","desc":"Piper PA-34 200 Seneca"},"D80":{"r":"N30FK","t":"RV7","f":"00","desc":"2012 VOICE OF VICTORY INC VANS RV7A"},"D82":{"r":"N30FM","t":"M20P","f":"00","desc":"Mooney M.20J Model MSE"},"D88":{"r":"N30FT","t":"FA20","f":"00","desc":"Dassault Falcon 20 F"},"D8F":{"r":"N30G","t":"BE18","f":"00","desc":"Beech 18 D \/ S"},"D91":{"r":"N30GB","t":"BE18","f":"00","desc":"Beech 18 H"},"D92":{"r":"N30GC","t":"ASTR","f":"00","desc":"1993 ISRAEL AIRCRAFT INDUSTRIES 1125 WESTWIND ASTRA"},"D93":{"r":"N30GD","t":"GLF4","f":"00","desc":"1993 GULFSTREAM AEROSPACE G-IV"},"D94":{"r":"N30GE","t":"C182","f":"00","desc":"1976 CESSNA 182P"},"D97":{"r":"N30GH","t":"BE36","f":"00","desc":"2007 RAYTHEON AIRCRAFT COMPANY G36"},"D98":{"r":"N30GJ","t":"LJ60","f":"00","desc":"2012 LEARJET INC 60"},"DA1":{"r":"N30GT","t":"BE9T","f":"00","desc":"1980 BEECH F90"},"DA7":{"r":"N30GZ","t":"SJ30","f":"00","desc":"SyberJet Aircraft SJ-30 2"},"DAA":{"r":"N30HB","t":"C340","f":"00","desc":"CESSNA 340A"},"DAC":{"r":"N30HD","t":"C25A","f":"00","desc":"525A"},"DAE":{"r":"N30HF","t":"B407","f":"00","desc":"2007 BELL 407"},"DBC":{"r":"N30HV","t":"BE30","f":"00","desc":"Beech King Air 300"},"DBE":{"r":"N30HX","t":"AS50","f":"00","desc":"Eurocopter Squirrel AS.350 B3"},"DC4":{"r":"N30JC","t":"A109","f":"00","desc":"2008 AGUSTA SPA A109S"},"DC6":{"r":"N30JE","t":"GLF4","f":"00","desc":"Gulfstream Aerospace GIV SP"},"DC7":{"r":"N30JF","t":"T6","f":"00","desc":"1958 NORTH AMERICAN SNJ-5"},"DCA":{"r":"N30JJ","t":"C172","f":"00","desc":"Cessna 172"},"DD1":{"r":"N30JR","t":"BE9L","f":"00","desc":"1996 RAYTHEON AIRCRAFT COMPANY C90A"},"DDD":{"r":"N30KC","t":"BE9L","f":"00","desc":"Beech King Air E90"},"DDE":{"r":"N30KD","t":"BE36","f":"00","desc":"RAYTHEON AIRCRAFT COMPANY A36"},"DF5":{"r":"N30LB","t":"F900","f":"00","desc":""},"DF6":{"r":"N30LC","t":"","f":"00","desc":"1971 CESSNA 310Q"},"DF9":{"r":"N30LF","t":"F2TH","f":"00","desc":"2007 DASSAULT AVIATION FALCON 2000EX"},"DFB":{"r":"N30LH","t":"GLF4","f":"00","desc":"1992 GULFSTREAM AEROSPACE G-IV"},"DFE":{"r":"N30LL","t":"BE58","f":"00","desc":"1982 BEECH 58P"},"E01":{"r":"N30LP","t":"C310","f":"00","desc":"1977 CESSNA 310R"},"E05":{"r":"N30LT","t":"C421","f":"00","desc":"Cessna 421C Golden Eagle"},"E06":{"r":"N30LU","t":"C172","f":"00","desc":"2005 CESSNA 172R"},"E07":{"r":"N30LV","t":"P28A","f":"00","desc":"Piper PA-28 161 Warrior II"},"E09":{"r":"N30LX","t":"GLF3","f":"10","desc":"1984 GULFSTREAM AEROSPACE G-1159A"},"E0D":{"r":"N30MA","t":"MU2","f":"00","desc":"1978 MITSUBISHI MU-2B-26A"},"E0F":{"r":"N30MC","t":"B350","f":"00","desc":"2006 RAYTHEON AIRCRAFT COMPANY B300"},"E16":{"r":"N30MK","t":"BE33","f":"00","desc":"Beech Bonanza F33A"},"E17":{"r":"N30ML","t":"PC12","f":"00","desc":"2012 PILATUS AIRCRAFT LTD PC-12\/47E"},"E18":{"r":"N30MM","t":"BE60","f":"00","desc":"Beech Duke B60"},"E19":{"r":"N30MN","t":"E55P","f":"00","desc":"EMBRAER EXECUTIVE AIRCRAFT INC EMB-505"},"E1A":{"r":"N30MP","t":"B721","f":"00","desc":"Boeing 727-21"},"E22":{"r":"N30MX","t":"","f":"00","desc":"2007 JACKSON DENNIS MARK 3 EXTRA"},"E2B":{"r":"N30NF","t":"C510","f":"00","desc":"2009 CESSNA 510"},"E31":{"r":"N30NM","t":"A109","f":"00","desc":"AGUSTA SPA A109E"},"E36":{"r":"N30NS","t":"","f":"00","desc":"Cessna Citation M2"},"E37":{"r":"N30NT","t":"AS50","f":"01","desc":"Eurocopter AS 350 B2"},"E3A":{"r":"N30NW","t":"PA30","f":"00","desc":"1964 PIPER PA-30"},"E3C":{"r":"N30NY","t":"S76","f":"00","desc":"1996 SIKORSKY S-76B"},"E3F":{"r":"N30PA","t":"LJ35","f":"00","desc":"Learjet 35A"},"E41":{"r":"N30PC","t":"LJ45","f":"00","desc":"2010 LEARJET INC 45"},"E42":{"r":"N30PD","t":"DHC2","f":"00","desc":"1957 DEHAVILLAND DHC-2"},"E4C":{"r":"N30PP","t":"","f":"00","desc":"ORCUTT CHARLES L GN-1 AIRCAMPER"},"E4D":{"r":"N30PQ","t":"LJ45","f":"00","desc":""},"E4E":{"r":"N30PR","t":"GLF2","f":"00","desc":"1968 GRUMMAN G-1159"},"E71":{"r":"N30RA","t":"C402","f":"00","desc":"Cessna 402C"},"E75":{"r":"N30RE","t":"BL17","f":"00","desc":"1979 BELLANCA 17-30A"},"E76":{"r":"N30RF","t":"BE33","f":"00","desc":"1978 BEECH F33C"},"E7E":{"r":"N30RP","t":"BE36","f":"00","desc":"Beech Bonanza A36"},"E84":{"r":"N30RV","t":"RV4","f":"00","desc":"1999 FUQUA BOB E RV4"},"E85":{"r":"N30RW","t":"C310","f":"00","desc":"Cessna 310R"},"E86":{"r":"N30RX","t":"EC35","f":"00","desc":"Eurocopter EC135 P2+"},"E89":{"r":"N30S","t":"P337","f":"00","desc":"1973 CESSNA T337G"},"E8C":{"r":"N30SC","t":"PA31","f":"00","desc":"1981 PIPER PA-31-350"},"E8E":{"r":"N30SE","t":"BE20","f":"00","desc":"Beech King Air B200"},"E90":{"r":"N30SG","t":"RV7","f":"00","desc":"2014 NEVADA FLYBOYS LLP RV-7A"},"E92":{"r":"N30SJ","t":"SJ30","f":"00","desc":"SyberJet Aircraft SJ-30 2"},"E94":{"r":"N30SL","t":"BE36","f":"00","desc":"Beech Bonanza A36"},"E95":{"r":"N30SM","t":"B350","f":"00","desc":"BEECH B300"},"E9B":{"r":"N30ST","t":"C25A","f":"00","desc":"2012 CESSNA 525A"},"E9C":{"r":"N30SU","t":"C172","f":"00","desc":"TEXTRON AVIATION INC 172S"},"EA2":{"r":"N30T","t":"C310","f":"00","desc":"1962 CESSNA 310G"},"EAC":{"r":"N30TK","t":"WW24","f":"00","desc":"1982 ISRAEL AIRCRAFT INDUSTRIES 1124A"},"EAD":{"r":"N30TL","t":"LJ45","f":"00","desc":""},"EB0":{"r":"N30TP","t":"PA31","f":"00","desc":"Piper PA-31 350 Navajo Chieftain"},"ECF":{"r":"N30UV","t":"","f":"00","desc":"ROTOR FX LLC RFX08"},"ED5":{"r":"N30VA","t":"B407","f":"01","desc":"2000 BELL 407"},"ED6":{"r":"N30VB","t":"R44","f":"00","desc":"Robinson R44 Raven II"},"EDC":{"r":"N30VH","t":"R22","f":"00","desc":"Robinson R22 Beta II"},"EE2":{"r":"N30VP","t":"H25B","f":"00","desc":"2009 HAWKER BEECHCRAFT CORP HAWKER 900XP"},"EE4":{"r":"N30VR","t":"C525","f":"00","desc":"Cessna 525"},"EEE":{"r":"N30WA","t":"M20T","f":"00","desc":""},"EEF":{"r":"N30WB","t":"BE35","f":"00","desc":"Beech Bonanza V35A"},"EF2":{"r":"N30WE","t":"TBM8","f":"00","desc":"2012 SOCATA TBM 700"},"EF4":{"r":"N30WG","t":"BE55","f":"00","desc":"1974 BEECH E-55"},"EFD":{"r":"N30WR","t":"GLF3","f":"00","desc":"1983 GULFSTREAM AEROSPACE G-1159A"},"F03":{"r":"N30WX","t":"A139","f":"00","desc":"2009 AGUSTA AEROSPACE CORP AW139"},"F04":{"r":"N30WY","t":"HUSK","f":"00","desc":"2007 AVIAT AIRCRAFT INC A-1B"},"F09":{"r":"N30XC","t":"CL30","f":"00","desc":""},"F11":{"r":"N30XL","t":"BE40","f":"00","desc":"1990 BEECH 400A"},"F18":{"r":"N30XT","t":"PA32","f":"00","desc":""},"F28":{"r":"N30YJ","t":"BE35","f":"00","desc":"Beech Bonanza N35"},"F2F":{"r":"N30YR","t":"C172","f":"00","desc":"1997 CESSNA 172R"},"F50":{"r":"N30ZZ","t":"P28A","f":"00","desc":"Piper PA-28 151 Cherokee Warrior"},"F52":{"r":"N300A","t":"GLF5","f":"00","desc":"2010 GULFSTREAM AEROSPACE GV-SP (G550)"},"F53":{"r":"N300AA","t":"LJ45","f":"00","desc":"LEARJET INC 45"},"F54":{"r":"N300AB","t":"BE35","f":"00","desc":"Beech Bonanza V35"},"F57":{"r":"N300AE","t":"TBM7","f":"00","desc":"SOCATA TBM 700"},"F5B":{"r":"N300AJ","t":"BE20","f":"00","desc":"1981 BEECH B200"},"F5C":{"r":"N300AK","t":"C56X","f":"00","desc":"2002 CESSNA 560XL"},"F5F":{"r":"N300AN","t":"LJ45","f":"00","desc":"Bombardier Learjet 45"},"F61":{"r":"N300AQ","t":"LJ45","f":"00","desc":""},"F63":{"r":"N300AS","t":"BE55","f":"00","desc":"1975 BEECH B-55"},"F64":{"r":"N300AT","t":"GLID","f":"00","desc":"2012 ALEXANDER SCHLEICHER GMBH & CO ASW 27-18"},"F66":{"r":"N300AV","t":"CL30","f":"00","desc":"2006 BOMBARDIER INC BD-100-1A10"},"F67":{"r":"N300AW","t":"BE9L","f":"00","desc":"1999 RAYTHEON AIRCRAFT COMPANY C90A"},"F6A":{"r":"N300AZ","t":"TBM7","f":"00","desc":"2004 SOCATA TBM 700"},"F6B":{"r":"N300B","t":"BE55","f":"00","desc":"Beech 95-B55"},"F6C":{"r":"N300BA","t":"FA20","f":"00","desc":"1968 DASSAULT\/SUD FAN JET FALCON"},"F6D":{"r":"N300BB","t":"C25C","f":"00","desc":"2014 CESSNA 525C"},"F6E":{"r":"N300BC","t":"CL30","f":"00","desc":"2005 BOMBARDIER INC BD-100-1A10"},"F6F":{"r":"N300BD","t":"C310","f":"00","desc":"Cessna 310R Turbo"},"F73":{"r":"N300BH","t":"PA32","f":"00","desc":"1980 PIPER PA-32-301"},"F76":{"r":"N300BL","t":"E300","f":"00","desc":"Extra EA.300"},"F7B":{"r":"N300BR","t":"C421","f":"00","desc":"CESSNA 421C"},"F7F":{"r":"N300BV","t":"C525","f":"00","desc":"2001 CESSNA 525"},"F80":{"r":"N300BW","t":"C182","f":"00","desc":"1965 CESSNA 182J"},"F81":{"r":"N300BX","t":"M20T","f":"00","desc":"2000 MOONEY M20M"},"F83":{"r":"N300BZ","t":"CL30","f":"00","desc":"2011 BOMBARDIER INC BD-100-1A10"},"F85":{"r":"N300CA","t":"P28A","f":"00","desc":"Piper PA-28 180 Cherokee"},"F89":{"r":"N300CE","t":"PAY1","f":"00","desc":"1980 PIPER PA-31T1"},"F8B":{"r":"N300CG","t":"C414","f":"00","desc":"Cessna 414A Chancellor"},"F8E":{"r":"N300CK","t":"H269","f":"00","desc":""},"F91":{"r":"N300CN","t":"PA31","f":"00","desc":"Piper PA31-325"},"F92":{"r":"N300CP","t":"P32R","f":"00","desc":""},"F93":{"r":"N300CQ","t":"H25B","f":"00","desc":"Hawker 800XP"},"F94":{"r":"N300CR","t":"GLF4","f":"00","desc":"2000 GULFSTREAM AEROSPACE G-IV"},"F95":{"r":"YV521T","t":"C55B","f":"00","desc":"Cessna Citation Bravo"},"F96":{"r":"N300CT","t":"BE55","f":"00","desc":"1981 BEECH E-55"},"F99":{"r":"N300CW","t":"BE30","f":"00","desc":"Beech King Air 300"},"F9A":{"r":"N300CX","t":"TBM7","f":"00","desc":""},"F9E":{"r":"N300DA","t":"C56X","f":"00","desc":"CESSNA 560XL"},"F9F":{"r":"N300DB","t":"PA32","f":"00","desc":"1979 PIPER PA-32-300"},"FA0":{"r":"N300DC","t":"P28A","f":"00","desc":"2003 PIPER PA-28-161"},"FA2":{"r":"N300DE","t":"PA34","f":"00","desc":"Piper PA-34 200T Seneca II"},"FA4":{"r":"N300DG","t":"CL30","f":"00","desc":"2005 BOMBARDIER INC BD-100-1A10"},"FA5":{"r":"N300DH","t":"CL30","f":"00","desc":"BOMBARDIER INC BD-100-1A10"},"FA7":{"r":"N300DK","t":"RV12","f":"00","desc":"Vans RV-12"},"FA9":{"r":"N300DM","t":"BE9T","f":"00","desc":"Beech King Air F90"},"FAF":{"r":"N300DT","t":"PA32","f":"00","desc":"1978 PIPER PA-32-300"},"FB8":{"r":"N300EB","t":"","f":"00","desc":"1974 CESSNA 310R"},"FBC":{"r":"N300EF","t":"P28A","f":"00","desc":"Piper PA-28 151 Cherokee Warrior"},"FBE":{"r":"N300EH","t":"DHC6","f":"00","desc":""},"FBF":{"r":"N300EJ","t":"C310","f":"00","desc":"Cessna 310Q"},"FC2":{"r":"N300EM","t":"C182","f":"00","desc":"Cessna 182J Skylane"},"FC6":{"r":"N300ER","t":"CL30","f":"00","desc":"2013 BOMBARDIER INC BD-100-1A10"},"FC7":{"r":"N300ES","t":"GLF4","f":"00","desc":"Gulfstream 450"},"FC8":{"r":"N300ET","t":"C25B","f":"00","desc":""},"FC9":{"r":"N300EU","t":"CL30","f":"00","desc":"2012 BOMBARDIER INC BD-100-1A10"},"FCC":{"r":"N300EX","t":"E300","f":"00","desc":"1995 EXTRA FLUGZEUGBAU GMBH EA 300\/L"},"FD1":{"r":"N300FB","t":"EPIC","f":"00","desc":"Epic Aircraft Company Epic LT"},"FD2":{"r":"N300FC","t":"C525","f":"00","desc":"1998 CESSNA 525"},"FD8":{"r":"N300FJ","t":"E55P","f":"00","desc":"2011 EMBRAER-EMPRESA BRASILEIRA DE EMB-505"},"FDA":{"r":"N300FL","t":"E55P","f":"00","desc":"2010 EMBRAER-EMPRESA BRASILEIRA DE EMB-505"},"FDC":{"r":"N300FN","t":"CL30","f":"00","desc":"Bombardier Challenger 300"},"FDD":{"r":"N300FP","t":"E55P","f":"00","desc":"2015 EMBRAER EXECUTIVE AIRCRAFT INC EMB-505"},"FDF":{"r":"N300FR","t":"E300","f":"00","desc":"Extra EA.300"},"FE0":{"r":"N300FS","t":"F2TH","f":"00","desc":"2009 DASSAULT AVIATION FALCON 2000EX"},"FE1":{"r":"N300FT","t":"COUR","f":"00","desc":"Helio Super Courier H.295"},"FE2":{"r":"N300FU","t":"E300","f":"00","desc":"1992 EXTRA FLUGZEUGBAU GMBH EA-300"},"FE8":{"r":"N300G","t":"BE36","f":"00","desc":"2013 HAWKER BEECHCRAFT CORP G36"},"FEA":{"r":"N300GB","t":"BE40","f":"00","desc":"1999 RAYTHEON AIRCRAFT COMPANY 400A"},"FEC":{"r":"N300GD","t":"C425","f":"00","desc":"1980 CESSNA 425"},"FEE":{"r":"N300GF","t":"LJ40","f":"00","desc":"2009 LEARJET INC 45"},"FF0":{"r":"N300GH","t":"C550","f":"00","desc":"1978 CESSNA 550"},"FF4":{"r":"N300GM","t":"CL30","f":"00","desc":""},"FF6":{"r":"N300GP","t":"CL30","f":"00","desc":"2009 BOMBARDIER INC BD-100-1A10"},"FF9":{"r":"N300GS","t":"GLAS","f":"00","desc":"1989 SPECKETER GARY GLASAIR III"},"FFC":{"r":"N300GV","t":"E55P","f":"00","desc":"2012 EMBRAER S A EMB-505"}}